Workbook

Sheet 1. Trade-Off-QA
A1: Atributos propuestos por usuario | Q1: Atributos Promediados entre usuario y Arquitectos
A2: Atributos de Calidad | B2: Prioridad | C2: <----Prioridad----> | Q2: Atributos de Calidad | R2: Prioridad | S2: <----Prioridad---->
C3: 1 | D3: 2 | E3: 3 | F3: 4 | G3: 5 | H3: 6 | I3: 7 | J3: 8 | K3: 9 | L3: 10 | M3: 11 | N3: 12 | O3: 13 | S3: 1 | T3: 2 | U3: 3 | V3: 4 | W3: 5 | X3: 6 | Y3: 7 | Z3: 8 | AA3: 9 | AB3: 10 | AC3: 11 | AD3: 12 | AE3: 13
A4: Confiabilidad | B4: 1 | Q4: Confiabilidad | R4: 1
A5: Experiencia de Usuario | B5: 2 | Q5: Capacidad para ser Auditado | R5: 2
A6: Disponibilidad | B6: 3 | Q6: Rendimiento | R6: 3
A7: Seguridad | B7: 4 | Q7: Seguridad | R7: 4
A8: Rendimiento | B8: 5 | Q8: Experiencia de Usuario | R8: 5
A9: Capacidad para ser Soportado | B9: 6 | Q9: Disponibilidad | R9: 6
A10: Capacidad para ser Administrado | B10: 7 | Q10: Escalabilidad | R10: 7
A11: Portabilidad | B11: 8 | Q11: Capacidad para ser Administrado | R11: 8
A12: Capacidad | B12: 9 | Q12: Portabilidad | R12: 9
A13: Accesibilidad | B13: 10 | Q13: Capacidad | R13: 10
A14: Capacidad para ser Auditado | B14: 11 | Q14: Capacidad para ser Soportado | R14: 11
A15: Escalabilidad | B15: 12 | Q15: Interoperatividad | R15: 12
A16: Interoperatividad | B16: 13 | Q16: Accesibilidad | R16: 13
A18: Atributos Propuestos por Arquitectos
A19: Atributos de Calidad | B19: Prioridad | C19: <----Prioridad---->
C20: 1 | D20: 2 | E20: 3 | F20: 4 | G20: 5 | H20: 6 | I20: 7 | J20: 8 | K20: 9 | L20: 10 | M20: 11 | N20: 12 | O20: 13
A21: Confiabilidad | B21: 1
A22: Disponibilidad | B22: 2
A23: Capacidad | B23: 3
A24: Rendimiento | B24: 4
A25: Capacidad para ser Auditado | B25: 5
A26: Capacidad para ser Administrado | B26: 6
A27: Interoperatividad | B27: 7
A28: Experiencia de Usuario | B28: 8
A29: Seguridad | B29: 9
A30: Portabilidad | B30: 10
A31: Capacidad para ser Soportado | B31: 11
A32: Accesibilidad | B32: 12
A33: Escalabilidad | B33: 13

Sheet 2. Priorización-QA
A1: Atributos de calidad | B1: <---Actores---->
B2: Supervisor de Campo | C2: Gerente de producción | D2: Administrador del sistema | E2: Puntuación total | F2: Porcentaje
A3: Confiabilidad | B3: 1 | C3: 1 | D3: 1 | E3: =SUM(B3:D3) -> 3 | F3: =E3/E$16 -> 0.010989011
A4: Disponibilidad | B4: 2 | C4: 2 | D4: 7 | E4: =SUM(B4:D4) -> 11 | F4: =E4/E$16 -> 0.04029304
A5: Rendimiento | B5: 3 | C5: 5 | D5: 9 | E5: =SUM(B5:D5) -> 17 | F5: =E5/E$16 -> 0.062271062
A6: Capacidad para ser Auditado | B6: 9 | C6: 4 | D6: 4 | E6: =SUM(B6:D6) -> 17 | F6: =E6/E$16 -> 0.062271062
A7: Capacidad | B7: 11 | C7: 3 | D7: 5 | E7: =SUM(B7:D7) -> 19 | F7: =E7/E$16 -> 0.06959707
A8: Capacidad para ser Administrado | B8: 13 | C8: 7 | D8: 3 | E8: =SUM(B8:D8) -> 23 | F8: =E8/E$16 -> 0.084249084
A9: Experiencia de Usuario | B9: 6 | C9: 6 | D9: 12 | E9: =SUM(B9:D9) -> 24 | F9: =E9/E$16 -> 0.087912088
A10: Seguridad | B10: 10 | C10: 8 | D10: 6 | E10: =SUM(B10:D10) -> 24 | F10: =E10/E$16 -> 0.087912088
A11: Interoperatividad | B11: 5 | C11: 10 | D11: 10 | E11: =SUM(B11:D11) -> 25 | F11: =E11/E$16 -> 0.091575092
A12: Escalabilidad | B12: 8 | C12: 9 | D12: 8 | E12: =SUM(B12:D12) -> 25 | F12: =E12/E$16 -> 0.091575092
A13: Capacidad para ser Soportado | B13: 12 | C13: 13 | D13: 2 | E13: =SUM(B13:D13) -> 27 | F13: =E13/E$16 -> 0.098901099
A14: Portabilidad | B14: 4 | C14: 11 | D14: 13 | E14: =SUM(B14:D14) -> 28 | F14: =E14/E$16 -> 0.1025641
A15: Accesibilidad | B15: 7 | C15: 12 | D15: 11 | E15: =SUM(B15:D15) -> 30 | F15: =E15/E$16 -> 0.10989011
B16: =SUM(B3:B15) -> 91 | C16: =SUM(C3:C15) -> 91 | D16: =SUM(D3:D15) -> 91 | E16: =SUM(E3:E15) -> 273 | F16: =SUM(F3:F15) -> 1
E18: |

Sheet 3. Caracterización
A1: Atributo de calidad | B1: Pregunta | C1: Respuesta Juan | D1: Respuesta Jeronimo | E1: Respuesta Cliente | F1: Nota | G1: Tomador de datos | H1: Produccion | I1: Administrador | J1: Puntaje Total | K1: Seleccionada (Top 65)
A2: Confiabilidad | B2: ¿Se necesita verificar que la información sea correcta de manera individual con cada dato tomado? | C2: NO | D2: NO | E2: SI | J2: =SUM(G2:I2) -> 0
A3: Confiabilidad | B3: ¿Se necesita verificar que la información sea correcta de manera que se agrupe la información por variedad? | C3: SI | D3: SI | E3: SI | J3: =SUM(G3:I3) -> 0
A4: Confiabilidad | B4: ¿Se necesita verificar que la información sea correcta de manera que se agrupe la información por sección de la cama? | C4: SI | D4: SI | E4: NO | J4: =SUM(G4:I4) -> 0
A5: Confiabilidad | B5: ¿Se necesita verificar que la información sea correcta de manera que se agrupe la información por cama? | C5: SI | D5: SI | E5: SI | J5: =SUM(G5:I5) -> 0
A6: Confiabilidad | B6: ¿Se necesita verificar que la información sea correcta de manera que se agrupe la información por bloque? | C6: NO | D6: SI | E6: SI | F6: NO TAN IMPORTANTE | J6: =SUM(G6:I6) -> 0
A7: Confiabilidad | B7: ¿Se necesita verificar que la información sea correcta de manera que se agrupe la información por finca y por jornada completa? | C7: SI | D7: SI | E7: SI | H7: 2 | J7: =SUM(G7:I7) -> 2 | K7: SI
A8: Confiabilidad | B8: ¿Se necesita una confirmación final que muestre todo lo capturado antes de darlo por guardado? | C8: SI | D8: SI | E8: NO | J8: =SUM(G8:I8) -> 0
A9: Confiabilidad | B9: ¿Se necesita que el sistema impida cerrar la captura de una cama si quedaron campos sin diligenciar? | C9: SI | D9: SI | E9: NO | F9: HAY CAMPOS QUE NO SON CONCORDANTES CON OTROS | J9: =SUM(G9:I9) -> 0
A10: Confiabilidad | B10: ¿Se necesita que el sistema permita guardar una captura incompleta y marcarla como pendiente? | C10: SI | D10: SI | E10: SI | H10: 1 | J10: =SUM(G10:I10) -> 1 | K10: SI
A11: Confiabilidad | B11: ¿Se necesita que el sistema rechace un dato cuando está fuera del rango posible (por ejemplo, más tallos que plantas sembradas)? | C11: SI | D11: SI | E11: SI | G11: 3 | H11: 3 | J11: =SUM(G11:I11) -> 6 | K11: SI
A12: Confiabilidad | B12: ¿Se necesita que el sistema advierta, sin bloquear, cuando un dato se aleja mucho de lo que se ha capturado históricamente en esa misma cama? | C12: NO | D12: NO | E12: SI | J12: =SUM(G12:I12) -> 0
A13: Confiabilidad | B13: ¿Se necesita que el sistema muestre siempre el motivo por el cual rechazó un dato? | C13: SI | D13: SI | E13: SI | H13: 1 | J13: =SUM(G13:I13) -> 1 | K13: SI
A14: Confiabilidad | B14: ¿Se necesita que los rangos y las reglas de validación se puedan cambiar sin depender de una nueva versión de la aplicación? | C14: SI | D14: SI | E14: SI | H14: 3 | I14: 1 | J14: =SUM(G14:I14) -> 4 | K14: SI
A15: Confiabilidad | B15: ¿Se necesita que las reglas de validación funcionen igual estando sin conexión que estando conectado? | C15: SI | D15: SI | E15: SI | G15: 1 | J15: =SUM(G15:I15) -> 1 | K15: SI
A16: Confiabilidad | B16: ¿Se necesita que el sistema avise cuando se intenta capturar dos veces la misma cama el mismo día? | C16: SI | D16: SI | E16: SI | G16: 2 | J16: =SUM(G16:I16) -> 2 | K16: SI
A17: Confiabilidad | B17: ¿Se necesita que el sistema avise cuando una cama lleva más días de lo normal sin ser capturada? | C17: SI | D17: SI | E17: SI | J17: =SUM(G17:I17) -> 0
A18: Confiabilidad | B18: ¿Se necesita que el sistema impida registrar una labor sobre una cama que ya fue erradicada? | C18: NO | D18: NO | E18: NO | F18: DEPENDE DEL TIPO DE INGRESO DE DATO | J18: =SUM(G18:I18) -> 0
A19: Confiabilidad | B19: ¿Se necesita que el sistema bloquee la captura cuando detecta que la fecha y la hora del dispositivo fueron alteradas? | C19: SI | D19: SI | E19: SI | G19: 1 | I19: 2 | J19: =SUM(G19:I19) -> 3 | K19: SI
A20: Confiabilidad | B20: ¿Se necesita realizar la captura de datos de manera progresiva y guiada pantalla por pantalla (primero se selecciona bloque, luego cama, luego se captura lote y fecha de siembra, después las variedades plantadas)? | C20: NO | D20: NO | E20: NO | J20: =SUM(G20:I20) -> 0
A21: Confiabilidad | B21: ¿Se necesita realizar la captura de datos con una plantilla predefinida que use una estructura similar a las plantillas de papel utilizadas previamente? | C21: SI | D21: SI | E21: SI | G21: 1 | J21: =SUM(G21:I21) -> 1 | K21: NO
A22: Confiabilidad | B22: ¿Se necesita que la estructura de captura sea siempre la misma para todos los bloques de la finca? | C22: NO | D22: NO | E22: SI | J22: =SUM(G22:I22) -> 0
A23: Confiabilidad | B23: ¿Se necesita que la estructura de captura pueda cambiar según la variedad que se esté trabajando? | C23: SI | D23: SI | E23: NO | F23: PUEDEN HABER DATOS EN BLANCO | J23: =SUM(G23:I23) -> 0
A24: Confiabilidad | B24: ¿Se necesita que el sistema proponga automáticamente el valor capturado la última vez para esa misma cama? | C24: NO | D24: NO | E24: NO | J24: =SUM(G24:I24) -> 0
A25: Confiabilidad | B25: ¿Se necesita que el orden de captura siga el recorrido físico que se hace dentro del bloque? | C25: NO | D25: NO | E25: NO | J25: =SUM(G25:I25) -> 0
A26: Confiabilidad | B26: ¿Se necesita que el sistema indique en todo momento cuántas camas faltan por capturar en la jornada? | C26: NO | D26: NO | E26: NO | J26: =SUM(G26:I26) -> 0
A27: Confiabilidad | B27: ¿Se necesita poder corregir un dato ya capturado antes de que se sincronice? | C27: SI | D27: SI | E27: SI | G27: 4 | J27: =SUM(G27:I27) -> 4 | K27: SI
A28: Confiabilidad | B28: ¿Se necesita poder corregir un dato después de que se sincronizó? | C28: SI | D28: SI | E28: SI | I28: 1 | J28: =SUM(G28:I28) -> 1 | K28: SI
A29: Confiabilidad | B29: ¿Se necesita que al corregir un dato se conserve visible el valor original? | C29: NO | D29: NO | E29: NO | J29: =SUM(G29:I29) -> 0
A30: Confiabilidad | B30: ¿Se necesita que toda corrección exija escribir un motivo? | C30: NO | D30: NO | E30: NO | J30: =SUM(G30:I30) -> 0
A31: Confiabilidad | B31: ¿Se necesita que exista una fecha a partir de la cual la información ya no se pueda corregir? | C31: NO | D31: NO | E31: NO | J31: =SUM(G31:I31) -> 0
A32: Confiabilidad | B32: ¿Se necesita que, cuando dos capturas de la misma cama entran en conflicto, el sistema resuelva solo tomando la más reciente? | C32: NO | D32: NO | E32: NO | J32: =SUM(G32:I32) -> 0
A33: Confiabilidad | B33: ¿Se necesita que, cuando dos capturas de la misma cama entran en conflicto, el sistema deje ambas y pida que una persona decida? | C33: SI | D33: SI | E33: NO | F33: NO DEJA INGRESAR EL ULTIMO REGISTRO | J33: =SUM(G33:I33) -> 0
A34: Confiabilidad | B34: ¿Se necesita que quien capturó el dato se entere cuando su captura fue descartada o modificada por un conflicto? | C34: NO | D34: NO | E34: SI | J34: =SUM(G34:I34) -> 0
A35: Confiabilidad | B35: ¿Se necesita saber, sobre cada proyección, con qué datos y con qué parámetros fue calculada? | C35: SI | D35: SI | E35: SI | H35: 4 | J35: =SUM(G35:I35) -> 4 | K35: SI
A36: Confiabilidad | B36: ¿Se necesita que una misma proyección, recalculada meses después, dé exactamente el mismo resultado? | C36: NO | D36: NO | E36: SI | F36: SI NO SE MODIFICA SI | J36: =SUM(G36:I36) -> 0
A37: Confiabilidad | B37: ¿Se necesita que el sistema muestre cuánto se desvió la proyección anterior frente a lo que realmente se cortó? | C37: SI | D37: SI | E37: SI | F37: SOBRE LA MISMA PROYECCION | H37: 4 | J37: =SUM(G37:I37) -> 4 | K37: SI
A38: Confiabilidad | B38: ¿Se necesita que el sistema muestre un indicador del porcentaje de datos con error o pendientes de verificación? | C38: NO | D38: NO | E38: NO | J38: =SUM(G38:I38) -> 0
A39: Confiabilidad | B39: ¿Se necesita fijar una meta explícita de porcentaje máximo de error aceptable en la información capturada? | C39: SI | D39: NO | E39: NO | F39: NO PUEDE HABER ERRORES | J39: =SUM(G39:I39) -> 0
A40: Confiabilidad | B40: ¿Se necesita que el sistema distinga la información verificada de la que todavía no lo ha sido? | C40: NO | D40: NO | E40: NO | J40: =SUM(G40:I40) -> 0
A41: Confiabilidad | B41: ¿Se necesita que la información no verificada quede excluida de las proyecciones hasta que se verifique? | C41: SI | D41: SI | E41: NO | J41: =SUM(G41:I41) -> 0
A42: Confiabilidad | B42: ¿Se necesita seguir llenando el formato en papel en paralelo durante los primeros meses de uso? | C42: SI | D42: SI | E42: SI | J42: =SUM(G42:I42) -> 0
A43: Confiabilidad | B43: ¿Se necesita que el sistema permita comparar lo capturado en la aplicación contra el formato en papel del mismo día? | C43: SI | D43: SI | E43: SI | G43: 1 | J43: =SUM(G43:I43) -> 1 | K43: NO
A44: Confiabilidad | B44: ¿Se necesita que no se pierda ningún dato capturado bajo ninguna circunstancia? | C44: SI | D44: SI | E44: SI | G44: 5 | H44: 5 | J44: =SUM(G44:I44) -> 10 | K44: SI
A45: Confiabilidad | B45: ¿Se necesita que la información se conserve cuando el dispositivo se apaga por batería agotada a mitad de una captura? | C45: SI | D45: SI | E45: SI | G45: 4 | J45: =SUM(G45:I45) -> 4 | K45: SI
A46: Confiabilidad | B46: ¿Se necesita que la información se conserve cuando la aplicación se cierra de manera inesperada? | C46: SI | D46: SI | E46: SI | G46: 3 | J46: =SUM(G46:I46) -> 3 | K46: SI
A47: Confiabilidad | B47: ¿Se necesita que la información se conserve cuando el dispositivo se moja o se dañe y hay que cambiarlo? | C47: SI | D47: SI | E47: SI | J47: =SUM(G47:I47) -> 0
A48: Confiabilidad | B48: ¿Se necesita que una sincronización interrumpida a la mitad pueda retomarse sin duplicar ni perder información? | C48: SI | D48: SI | E48: SI | J48: =SUM(G48:I48) -> 0
A49: Confiabilidad | B49: ¿Se necesita que el sistema haga copias de respaldo de manera automática, sin que nadie lo solicite? | C49: SI | D49: SI | E49: SI | I49: 5 | J49: =SUM(G49:I49) -> 5 | K49: SI
A50: Confiabilidad | B50: ¿Se necesita que las copias de respaldo se hagan al menos una vez al día? | C50: SI | D50: NO | E50: SI | J50: =SUM(G50:I50) -> 0
A51: Confiabilidad | B51: ¿Se necesita poder devolver la información a como estaba en una fecha anterior? | C51: SI | D51: SI | E51: NO | J51: =SUM(G51:I51) -> 0
A52: Confiabilidad | B52: ¿Se necesita poder devolver la información de una sola finca sin tocar la de las demás? | C52: SI | D52: SI | E52: NO | J52: =SUM(G52:I52) -> 0
A53: Confiabilidad | B53: ¿Se necesita que la información nunca se elimine, ni siquiera cuando se erradica una cama? | C53: SI | D53: SI | E53: SI | J53: =SUM(G53:I53) -> 0
A54: Confiabilidad | B54: ¿Se necesita conservar tanto la información tal como se capturó como la información ya corregida? | C54: NO | D54: NO | E54: NO | F54: SOLO LA CORREGIDA | J54: =SUM(G54:I54) -> 0
A55: Confiabilidad | B55: ¿Se necesita que el sistema avise cuando una proyección se calculó con información incompleta? | C55: SI | D55: SI | E55: NO | J55: =SUM(G55:I55) -> 0
A56: Confiabilidad | B56: ¿Se necesita que el sistema impida publicar una proyección cuando faltan datos de bloques enteros? | C56: NO | D56: NO | E56: NO | F56: TODO DEBE ESTAR INGRESADO | J56: =SUM(G56:I56) -> 0
A57: Confiabilidad | B57: ¿Se necesita que exista una prueba periódica de que las copias de respaldo efectivamente sirven? | C57: SI | D57: SI | E57: NO | I57: 3 | J57: =SUM(G57:I57) -> 3 | K57: SI
A58: Confiabilidad | B58: ¿Se necesita que la aplicación avise cuando el almacenamiento del dispositivo está por llenarse? | C58: SI | D58: SI | E58: SI | G58: 2 | J58: =SUM(G58:I58) -> 2 | K58: SI
A59: Disponibilidad | B59: ¿Se necesita capturar información en el área de cultivo sin ninguna conexión de datos? | C59: SI | D59: SI | E59: SI | G59: 5 | J59: =SUM(G59:I59) -> 5 | K59: SI
A60: Disponibilidad | B60: ¿Se necesita capturar durante una jornada completa sin sincronizar en ningún momento? | C60: NO | D60: NO | E60: SI | J60: =SUM(G60:I60) -> 0
A61: Disponibilidad | B61: ¿Se necesita capturar durante tres días seguidos sin sincronizar? | C61: NO | D61: NO | E61: SI | J61: =SUM(G61:I61) -> 0
A62: Disponibilidad | B62: ¿Se necesita capturar durante una semana seguida sin sincronizar? | C62: NO | D62: NO | E62: SI | J62: =SUM(G62:I62) -> 0
A63: Disponibilidad | B63: ¿Se necesita capturar durante más de quince días sin sincronizar? | C63: NO | D63: NO | E63: SI | J63: =SUM(G63:I63) -> 0
A64: Disponibilidad | B64: ¿Se necesita poder consultar la información ya sincronizada aunque en ese momento no haya conexión? | C64: NO | D64: NO | E64: NO | J64: =SUM(G64:I64) -> 0
A65: Disponibilidad | B65: ¿Se necesita poder consultar la información desde la web aunque la aplicación de captura esté fuera de servicio? | C65: SI | D65: SI | E65: SI | J65: =SUM(G65:I65) -> 0
A66: Disponibilidad | B66: ¿Se necesita que la captura siga funcionando aunque el servicio en la nube esté caído? | C66: SI | D66: SI | E66: SI | G66: 1 | J66: =SUM(G66:I66) -> 1 | K66: SI
A67: Disponibilidad | B67: ¿Se necesita que exista un horario del día en el que el sistema no pueda estar fuera de servicio bajo ninguna circunstancia? | C67: NO | D67: NO | E67: SI | J67: =SUM(G67:I67) -> 0
A68: Disponibilidad | B68: ¿Se necesita que el sistema esté disponible los siete días de la semana? | C68: NO | D68: NO | E68: SI | J68: =SUM(G68:I68) -> 0
A69: Disponibilidad | B69: ¿Se necesita que el sistema esté disponible las veinticuatro horas del día? | C69: NO | D69: NO | E69: SI | J69: =SUM(G69:I69) -> 0
A70: Disponibilidad | B70: ¿Se necesita que exista un periodo del año (temporada alta) con una exigencia de disponibilidad mayor que el resto? | C70: SI | D70: SI | E70: SI | J70: =SUM(G70:I70) -> 0
A71: Disponibilidad | B71: ¿Se necesita que una interrupción del servicio se resuelva en menos de una hora? | C71: SI | D71: SI | E71: SI | J71: =SUM(G71:I71) -> 0
A72: Disponibilidad | B72: ¿Se necesita que una interrupción del servicio se resuelva dentro del mismo día? | C72: SI | D72: SI | E72: SI | J72: =SUM(G72:I72) -> 0
A73: Disponibilidad | B73: ¿Se necesita que las labores de mantenimiento se avisen con anticipación? | C73: SI | D73: SI | E73: SI | J73: =SUM(G73:I73) -> 0
A74: Disponibilidad | B74: ¿Se necesita que las labores de mantenimiento se hagan sin sacar el sistema de servicio? | C74: SI | D74: SI | E74: NO | J74: =SUM(G74:I74) -> 0
A75: Disponibilidad | B75: ¿Se necesita poder continuar la captura en otro dispositivo cuando el que se estaba usando deja de funcionar? | C75: SI | D75: SI | E75: NO | J75: =SUM(G75:I75) -> 0
A76: Disponibilidad | B76: ¿Se necesita que la información capturada en un dispositivo que se dañó o se perdió pueda recuperarse? | C76: NO | D76: SI | E76: SI | J76: =SUM(G76:I76) -> 0
A77: Disponibilidad | B77: ¿Se necesita que una falla que afecte a una finca no afecte a las demás fincas o empresas? | C77: SI | D77: SI | E77: SI | J77: =SUM(G77:I77) -> 0
A78: Disponibilidad | B78: ¿Se necesita que el sistema avise cuando un dispositivo lleva demasiado tiempo sin sincronizar? | C78: SI | D78: SI | E78: SI | G78: 3 | J78: =SUM(G78:I78) -> 3 | K78: SI
A79: Rendimiento | B79: ¿Se necesita que registrar una cama completa tome menos tiempo del que hoy toma llenarla en papel? | C79: SI | D79: SI | E79: NO | J79: =SUM(G79:I79) -> 0
A80: Rendimiento | B80: ¿Se necesita que registrar una cama completa tome menos de un minuto? | C80: SI | D80: SI | E80: NO | F80: * | J80: =SUM(G80:I80) -> 0
A81: Rendimiento | B81: ¿Se necesita que registrar una cama completa tome menos de treinta segundos? | C81: SI | D81: SI | E81: NO | J81: =SUM(G81:I81) -> 0
A82: Rendimiento | B82: ¿Se necesita poder capturar un bloque completo dentro de una sola jornada? | C82: SI | D82: SI | E82: NO | F82: *SOBRA | J82: =SUM(G82:I82) -> 0
A83: Rendimiento | B83: ¿Se necesita poder capturar la finca completa dentro de una sola jornada? | C83: SI | D83: SI | E83: NO | F83: *SOBRA | J83: =SUM(G83:I83) -> 0
A84: Rendimiento | B84: ¿Se necesita que cada dato quede guardado de inmediato, sin espera perceptible? | C84: SI | D84: SI | E84: SI | G84: 2 | J84: =SUM(G84:I84) -> 2 | K84: SI
A85: Rendimiento | B85: ¿Se necesita que el paso de una pantalla a la siguiente sea inmediato aun sin conexión? | C85: SI | D85: SI | E85: SI | F85: * | G85: 2 | J85: =SUM(G85:I85) -> 2 | K85: SI
A86: Rendimiento | B86: ¿Se necesita que buscar una cama por su código dé resultado de inmediato? | C86: SI | D86: SI | E86: NO | F86: LIGERO, NO DE INMEDIATO | J86: =SUM(G86:I86) -> 0
A87: Rendimiento | B87: ¿Se necesita que la sincronización de una jornada completa termine en menos de cinco minutos? | C87: NO | D87: NO | E87: NO | J87: =SUM(G87:I87) -> 0
A88: Rendimiento | B88: ¿Se necesita que la sincronización ocurra en segundo plano, sin impedir seguir capturando? | C88: SI | D88: SI | E88: SI | F88: SERIA EL IDEAL | J88: =SUM(G88:I88) -> 0
A89: Rendimiento | B89: ¿Se necesita que muchos dispositivos puedan sincronizar al mismo tiempo al terminar la jornada sin que el sistema se degrade? | C89: SI | D89: SI | E89: SI | G89: 1 | I89: 1 | J89: =SUM(G89:I89) -> 2 | K89: SI
A90: Rendimiento | B90: ¿Se necesita que la información sincronizada se vea reflejada en la consulta web de inmediato? | C90: NO | D90: NO | E90: SI | J90: =SUM(G90:I90) -> 0
A91: Rendimiento | B91: ¿Se necesita que la información sincronizada se vea reflejada en la consulta web dentro de la misma hora? | C91: SI | D91: SI | E91: SI | H91: 1 | J91: =SUM(G91:I91) -> 1 | K91: SI
A92: Rendimiento | B92: ¿Se necesita que la información sincronizada se vea reflejada al día siguiente? | C92: SI | D92: SI | E92: SI | J92: =SUM(G92:I92) -> 0
A93: Rendimiento | B93: ¿Se necesita que un reporte de un mes se genere en menos de diez segundos? | C93: NO | D93: NO | E93: NO | J93: =SUM(G93:I93) -> 0
A94: Rendimiento | B94: ¿Se necesita que un reporte que abarque varios años se genere sin espera significativa? | C94: NO | D94: NO | E94: NO | J94: =SUM(G94:I94) -> 0
A95: Rendimiento | B95: ¿Se necesita que la proyección se recalcule en el momento en que llega información nueva? | C95: SI | D95: SI | E95: SI | H95: 5 | J95: =SUM(G95:I95) -> 5 | K95: SI
A96: Rendimiento | B96: ¿Se necesita que la proyección se recalcule una vez al día en un horario fijo? | C96: NO | D96: NO | E96: NO | J96: =SUM(G96:I96) -> 0
A97: Rendimiento | B97: ¿Se necesita que la aplicación funcione con fluidez en dispositivos de gama baja o de varios años de antigüedad? | C97: NO | D97: NO | E97: NO | J97: =SUM(G97:I97) -> 0
A98: Rendimiento | B98: ¿Se necesita que la aplicación no agote la batería del dispositivo antes de terminar la jornada? | C98: SI | D98: SI | E98: NO | J98: =SUM(G98:I98) -> 0
A99: Rendimiento | B99: ¿Se necesita que el rendimiento se mantenga igual en temporada alta que en el resto del año? | C99: SI | D99: SI | E99: SI | H99: 1 | J99: =SUM(G99:I99) -> 1 | K99: SI
A100: Capacidad para ser Auditado | B100: ¿Se necesita saber quién capturó cada dato? | C100: SI | D100: SI | E100: SI | J100: =SUM(G100:I100) -> 0
...

Sheet 4, Lluvia-de-Escenarios
A1: ID | B1: Rank | C1: Atributo de calidad | D1: Pregunta (planteamiento corregido) | E1: Fuente | F1: Estímulo | G1: Artefacto | H1: Entorno | I1: Respuesta | J1: Medida de respuesta | K1: Escenario de calidad | L1: Observación
A2: ESC-01 | B2: 1 | C2: Confiabilidad | D2: Se necesita que ningún dato capturado en campo se pierda ante cierre inesperado, batería agotada, pérdida de conexión o fallo de sincronización. | E2: un supervisor de campo | F2: termina la captura de una cama y el dispositivo falla (batería agotada, cierre inesperado o pérdida de conexión) antes de sincronizar | G2: el almacenamiento local de la app de captura y su cola de sincronización | H2: en operación normal en campo, sin conexión de datos | I2: conserva el registro en el dispositivo y lo entrega al servidor en la siguiente sincronización, sin duplicarlo ni alterarlo | J2: 0 registros perdidos sobre el total capturado, 0 duplicados tras la sincronización y 100% de los registros recuperables tras reiniciar el dispositivo | K2: un supervisor de campo termina la captura de una cama y el dispositivo falla (batería agotada, cierre inesperado o pérdida de conexión) antes de sincronizar, sobre el almacenamiento local de la app de captura y su cola de sincronización, en operación normal en campo, sin conexión de datos. El sistema conserva el registro en el dispositivo y lo entrega al servidor en la siguiente sincronización, sin duplicarlo ni alterarlo, con 0 registros perdidos sobre el total capturado, 0 duplicados tras la sincronización y 100% de los registros recuperables tras reiniciar el dispositivo. | L2: El planteamiento original era una afirmación absoluta, sin estímulo ni medida. Se acotó a los eventos de falla concretos y a la tolerancia de pérdida cero ya medida con el cliente.
A3: ESC-02 | B3: 2 | C3: Confiabilidad | D3: Se necesita que un dato fuera del rango posible (por ejemplo, más tallos que plantas sembradas) sea rechazado en el momento de la captura, aun sin conexión. | E3: un supervisor de campo | F3: digita un valor que viola una regla de rango (tallos mayores que las plantas sembradas de la sección) | G3: el motor de validación embebido en la app de captura | H3: en campo, sin conexión | I3: rechaza el valor en pantalla, indica la regla violada y no permite guardar hasta corregirlo | J3: 100% de los valores fuera de rango rechazados en el propio dispositivo, respuesta visible en menos de 1 segundo y 0 registros fuera de rango llegando al servidor | K3: un supervisor de campo digita un valor que viola una regla de rango (tallos mayores que las plantas sembradas de la sección), sobre el motor de validación embebido en la app de captura, en campo, sin conexión. El sistema rechaza el valor en pantalla, indica la regla violada y no permite guardar hasta corregirlo, con 100% de los valores fuera de rango rechazados en el propio dispositivo, respuesta visible en menos de 1 segundo y 0 registros fuera de rango llegando al servidor. | L3: Estaba planteado como funcionalidad («que rechace»). Se replanteó como propiedad de confiabilidad verificable en el punto de captura y sin red.
A4: ESC-03 | B4: 3 | C4: Confiabilidad | D4: Se necesita que la información quede respaldada de forma automática y recuperable, sin que ninguna persona tenga que solicitarlo. | E4: el programador de respaldos del sistema | F4: dispara el respaldo al cumplirse el intervalo definido, sin intervención humana | G4: la base de datos de la empresa y su repositorio de respaldos | H4: en operación normal, incluida la temporada alta | I4: genera, cifra y verifica el respaldo y registra el resultado sin que nadie lo pida | J4: 100% de respaldos ejecutados dentro de su ventana, pérdida de datos 0 confirmada y restauración completa en 1 día o menos | K4: el programador de respaldos del sistema dispara el respaldo al cumplirse el intervalo definido, sin intervención humana, sobre la base de datos de la empresa y su repositorio de respaldos, en operación normal, incluida la temporada alta. El sistema genera, cifra y verifica el respaldo y registra el resultado sin que nadie lo pida, con 100% de respaldos ejecutados dentro de su ventana, pérdida de datos 0 confirmada y restauración completa en 1 día o menos. | L4: Se replanteó de «hacer copias» a la propiedad de recuperabilidad, atada a las tolerancias medidas: pérdida cero y 1 día para restaurar.
A5: ESC-04 | B5: 4 | C5: Disponibilidad | D5: Se necesita que la captura en el área de cultivo siga siendo posible durante toda la jornada sin ninguna conexión de datos. | E5: un supervisor de campo | F5: entra a un bloque sin cobertura y captura durante toda la jornada | G5: la app de captura en el dispositivo Android y su almacén local | H5: sin conexión, jornada completa en campo | I5: permite capturar, validar y guardar localmente todos los registros y los encola para sincronizar cuando vuelva la conexión | J5: 100% de las funciones de captura disponibles sin red, 0 registros perdidos y jornada completa (8 horas o más) sin conexión | K5: un supervisor de campo entra a un bloque sin cobertura y captura durante toda la jornada, sobre la app de captura en el dispositivo Android y su almacén local, sin conexión, jornada completa en campo. El sistema permite capturar, validar y guardar localmente todos los registros y los encola para sincronizar cuando vuelva la conexión, con 100% de las funciones de captura disponibles sin red, 0 registros perdidos y jornada completa (8 horas o más) sin conexión. | L5: El original describía una funcionalidad. Se replanteó como disponibilidad de la captura ante ausencia total de red durante toda la jornada.
A6: ESC-05 | B6: 5 | C6: Rendimiento | D6: Se necesita que la proyección quede actualizada poco después de que llega información nueva, sin esperar al ciclo semanal. | E6: los dispositivos de captura al cierre de jornada | F6: sincronizan la información de la jornada | G6: el motor de proyección y sus versiones publicadas | H6: al cierre de jornada, con los 3 dispositivos sincronizando, también en temporada alta (+60% de registros) | I6: recalcula la proyección afectada y publica una versión nueva conservando la anterior | J6: proyección actualizada en 1 hora o menos desde la sincronización, degradación máxima del 20% en temporada alta y 0 versiones anteriores sobrescritas | K6: los dispositivos de captura al cierre de jornada sincronizan la información de la jornada, sobre el motor de proyección y sus versiones publicadas, al cierre de jornada, con los 3 dispositivos sincronizando, también en temporada alta (+60% de registros). El sistema recalcula la proyección afectada y publica una versión nueva conservando la anterior, con proyección actualizada en 1 hora o menos desde la sincronización, degradación máxima del 20% en temporada alta y 0 versiones anteriores sobrescritas. | L6: «Que se recalcule» era funcionalidad. Se replanteó como latencia máxima de actualización, con conservación explícita de la versión anterior.
A7: ESC-06 | B7: 6 | C7: Capacidad para ser Administrado | D7: Se necesita que el administrador de la empresa pueda parametrizar el sistema sin poder alterar la información de producción ya capturada. | E7: un administrador de la empresa (el ingeniero de sistemas de la finca) | F7: intenta modificar un registro de siembra, corte o baja ya capturado | G7: el control de acceso y el registro de producción | H7: en operación normal | I7: rechaza la modificación, la deja registrada en la bitácora y ofrece la vía de corrección autorizada | J7: 100% de los intentos rechazados y registrados, 0 registros de producción modificados por ese rol y separación de deberes verificable en la matriz de permisos | K7: un administrador de la empresa (el ingeniero de sistemas de la finca) intenta modificar un registro de siembra, corte o baja ya capturado, sobre el control de acceso y el registro de producción, en operación normal. El sistema rechaza la modificación, la deja registrada en la bitácora y ofrece la vía de corrección autorizada, con 100% de los intentos rechazados y registrados, 0 registros de producción modificados por ese rol y separación de deberes verificable en la matriz de permisos. | L7: Estaba planteado como una restricción funcional. Se replanteó como escenario de administrabilidad con separación de deberes verificable.
A8: ESC-07 | B8: 7 | C8: Confiabilidad | D8: Se necesita que al cambiar los rangos y las reglas de validación se actualicen en los dispositivos sin depender de una nueva versión de la aplicación. | E8: un administrador de la empresa, con el valor aprobado por producción | F8: cambia un rango válido, un ciclo, un margen o una regla de validación y ejecuta la acción de guardar | G8: el catálogo de reglas y parámetros y su mecanismo de distribución a los dispositivos | H8: en operación normal, con los dispositivos ya en campo y posiblemente fuera de línea | I8: aplica la regla nueva sin publicar una versión de la aplicación y sin que nadie reinstale nada: la propaga a los dispositivos conectados y la deja en cola para los desconectados | J8: 0 despliegues de aplicación, vigencia en todos los dispositivos en menos de un ciclo de sincronización, 0% de rechazos por conflicto con otras reglas, 0 proyecciones históricas alteradas y 0 solicitudes al desarrollador | K8: un administrador de la empresa, con el valor aprobado por producción cambia un rango válido, un ciclo, un margen o una regla de validación y ejecuta la acción de guardar, sobre el catálogo de reglas y parámetros y su mecanismo de distribución a los dispositivos, en operación normal, con los dispositivos ya en campo y posiblemente fuera de línea. El sistema aplica la regla nueva sin publicar una versión de la aplicación y sin que nadie reinstale nada: la propaga a los dispositivos conectados y la deja en cola para los desconectados, con 0 despliegues de aplicación, vigencia en todos los dispositivos en menos de un ciclo de sincronización, 0% de rechazos por conflicto con otras reglas, 0 proyecciones históricas alteradas y 0 solicitudes al desarrollador. | L8: Es el escenario del ejemplo de referencia: estaba planteado como funcionalidad y se replanteó como escenario de calidad.
A9: ESC-08 | B9: 8 | C9: Confiabilidad | D9: Se necesita que un dato capturado y aún no sincronizado pueda corregirse en el dispositivo sin que se pierda el rastro de la corrección. | E9: un supervisor de campo | F9: detecta un error en un registro que todavía está en la cola local | G9: el registro local y la bitácora de cambios del dispositivo | H9: en campo, sin conexión | I9: permite corregir el valor, conserva el valor original y el motivo, y sincroniza ambos | J9: corrección posible en 3 toques o menos, 100% de las correcciones con valor anterior y autor registrados y 0 registros sincronizados sin trazabilidad | K9: un supervisor de campo detecta un error en un registro que todavía está en la cola local, sobre el registro local y la bitácora de cambios del dispositivo, en campo, sin conexión. El sistema permite corregir el valor, conserva el valor original y el motivo, y sincroniza ambos, con corrección posible en 3 toques o menos, 100% de las correcciones con valor anterior y autor registrados y 0 registros sincronizados sin trazabilidad. | L9: «Poder corregir» era funcionalidad. Se replanteó como confiabilidad con trazabilidad obligatoria de la corrección.
A10: ESC-09 | B10: 9 | C10: Confiabilidad | D10: Se necesita que toda proyección publicada sea reproducible: que se sepa con qué datos y con qué versión de parámetros fue calculada. | E10: un administrador de producción | F10: abre una proyección y pide su origen | G10: la versión de la proyección junto con el conjunto de datos y parámetros con que se calculó | H10: en operación normal, desde la consulta web | I10: muestra la versión de parámetros, el corte de datos y la fecha de cálculo, y permite recalcularla obteniendo el mismo resultado | J10: 100% de las proyecciones con versión de datos y de parámetros asociada, recálculo idéntico (diferencia 0) sobre la misma versión e información disponible en 3 clics o menos | K10: un administrador de producción abre una proyección y pide su origen, sobre la versión de la proyección junto con el conjunto de datos y parámetros con que se calculó, en operación normal, desde la consulta web. El sistema muestra la versión de parámetros, el corte de datos y la fecha de cálculo, y permite recalcularla obteniendo el mismo resultado, con 100% de las proyecciones con versión de datos y de parámetros asociada, recálculo idéntico (diferencia 0) sobre la misma versión e información disponible en 3 clics o menos. | L10: Se replanteó de una consulta a la propiedad de reproducibilidad de la proyección, que es lo que la hace defendible ante el cliente.
A11: ESC-10 | B11: 10 | C11: Confiabilidad | D11: Se necesita que la desviación entre lo proyectado y lo realmente cortado quede visible sobre la misma proyección, sin que nadie la calcule aparte. | E11: los datos reales de corte de un ciclo | F11: llegan al sistema al cerrarse el ciclo | G11: la proyección versionada y su indicador de desviación | H11: en operación normal, al cierre de ciclo | I11: calcula la desviación contra la versión de proyección que estaba vigente en ese momento y la muestra sobre la misma proyección | J11: desviación disponible en 1 día o menos tras el cierre del ciclo, 100% de los ciclos con desviación calculada y 0 comparaciones contra versiones recalculadas después | K11: los datos reales de corte de un ciclo llegan al sistema al cerrarse el ciclo, sobre la proyección versionada y su indicador de desviación, en operación normal, al cierre de ciclo. El sistema calcula la desviación contra la versión de proyección que estaba vigente en ese momento y la muestra sobre la misma proyección, con desviación disponible en 1 día o menos tras el cierre del ciclo, 100% de los ciclos con desviación calculada y 0 comparaciones contra versiones recalculadas después. | L11: Se precisó la nota del cliente («sobre la misma proyección») como comparación contra la versión vigente, nunca contra un recálculo posterior. Depende de ESC-45.
A12: ESC-11 | B12: 11 | C12: Confiabilidad | D12: Se necesita que la información capturada se conserve cuando el dispositivo se apaga por batería agotada a mitad de una captura. | E12: el dispositivo del supervisor de campo | F12: se apaga por batería agotada con una captura a medio diligenciar | G12: el almacén local de la app de captura | H12: en campo, sin conexión, con la jornada avanzada | I12: restaura la captura en el punto donde iba al encender y la marca como pendiente | J12: 0 registros perdidos, 1 campo por rehacer como máximo y restauración automática al abrir la app, sin acción del usuario | K12: el dispositivo del supervisor de campo se apaga por batería agotada con una captura a medio diligenciar, sobre el almacén local de la app de captura, en campo, sin conexión, con la jornada avanzada. El sistema restaura la captura en el punto donde iba al encender y la marca como pendiente, con 0 registros perdidos, 1 campo por rehacer como máximo y restauración automática al abrir la app, sin acción del usuario. | L12: Se conservó como escenario, agregando el estímulo de falla concreto y una medida de recuperación verificable.
A13: ESC-12 | B13: 12 | C13: Capacidad para ser Auditado | D13: Se necesita poder reconstruir la historia completa de una cama, desde la siembra hasta la erradicación, sin recurrir a los respaldos ni al equipo de desarrollo. | E13: un administrador de producción | F13: selecciona una cama y pide su historia | G13: la bitácora de eventos de la cama y de sus secciones | H13: en operación normal, sobre la historia en línea (5 años) | I13: entrega la secuencia completa de siembra, cortes, bajas y erradicaciones con fecha, autor y motivo | J13: 100% de los eventos presentes y ordenados, consulta en 5 segundos o menos para los últimos 5 años y 0 solicitudes al equipo de desarrollo | K13: un administrador de producción selecciona una cama y pide su historia, sobre la bitácora de eventos de la cama y de sus secciones, en operación normal, sobre la historia en línea (5 años). El sistema entrega la secuencia completa de siembra, cortes, bajas y erradicaciones con fecha, autor y motivo, con 100% de los eventos presentes y ordenados, consulta en 5 segundos o menos para los últimos 5 años y 0 solicitudes al equipo de desarrollo. | L13: «Poder ver» era funcionalidad. Se replanteó como auditabilidad completa y autosuficiente, sin depender de restaurar respaldos.
... A66: ESC-65 | B66: 65 | C66: Capacidad | D66: Se necesita que el dispositivo tenga el catálogo completo de la finca antes de salir a capturar, para que nada dependa de la red en el campo. | E66: un supervisor de campo | F66: prepara el dispositivo antes de salir al cultivo | G66: el catálogo local (camas, secciones, variedades, grados y reglas) | H66: en la finca, con conexión, antes de iniciar la jornada | I66: descarga y verifica el catálogo completo y avisa si está incompleto o desactualizado | J66: descarga completa en 5 minutos o menos, 100% del catálogo de la finca disponible localmente y aviso bloqueante si falta algo antes de salir | K66: un supervisor de campo prepara el dispositivo antes de salir al cultivo, sobre el catálogo local (camas, secciones, variedades, grados y reglas), en la finca, con conexión, antes de iniciar la jornada. El sistema descarga y verifica el catálogo completo y avisa si está incompleto o desactualizado, con descarga completa en 5 minutos o menos, 100% del catálogo de la finca disponible localmente y aviso bloqueante si falta algo antes de salir. | L66: Se replanteó como precondición verificable de la operación sin conexión: es lo que sostiene a ESC-04 y ESC-37.
A68: Cómo leer esta hoja. Cada fila es uno de los 65 escenarios priorizados en la hoja «Top 65 - Priorizadas», con el planteamiento corregido y documentado en las seis partes del escenario de calidad (fuente, estímulo, artefacto, entorno, respuesta y medida de respuesta). La corrección siguió tres reglas: (1) lo que estaba escrito como funcionalidad («¿se necesita que el sistema haga X?») se reescribió como una propiedad de calidad observable; (2) todo escenario recibió un estímulo concreto y una medida de respuesta verificable, usando los números ya medidos con el cliente (pérdida de datos cero, 1 hora de tolerancia a fallo, 1 día para restaurar, 8 días de latencia actual, 2% de error de captura, +60% de volumen en temporada alta, 1 hora/día del supervisor); (3) donde el planteamiento chocaba con una decisión vigente o con una brecha abierta, el escenario se escribió igual y la contradicción quedó anotada en la columna «Observación» (ver ESC-16 sobre instalación en servidores propios, ESC-29 sobre Power BI, ESC-26, ESC-34, ESC-44 y ESC-62). La columna «Escenario de calidad» es la redacción en prosa que resulta de unir las seis partes.

Sheet Top 65 - Priorizadas
A1: Rank | B1: Atributo de calidad | C1: Pregunta | D1: Tomador de datos | E1: Producción | F1: Administrador | G1: Puntaje Total
A2: 1 | B2: ='3. Caracterización'!A44 -> Confiabilidad | C2: ='3. Caracterización'!B44 -> ¿Se necesita que no se pierda ningún dato capturado bajo ninguna circunstancia? | D2: ='3. Caracterización'!G44 -> 5 | E2: ='3. Caracterización'!H44 -> 5 | F2: ='3. Caracterización'!I44 -> 0 | G2: =SUM(D2:F2) -> 10
A3: 2 | B3: ='3. Caracterización'!A11 -> Confiabilidad | C3: ='3. Caracterización'!B11 -> ¿Se necesita que el sistema rechace un dato cuando está fuera del rango posible (por ejemplo, más tallos que plantas sembradas)? | D3: ='3. Caracterización'!G11 -> 3 | E3: ='3. Caracterización'!H11 -> 3 | F3: ='3. Caracterización'!I11 -> 0 | G3: =SUM(D3:F3) -> 6
A4: 3 | B4: ='3. Caracterización'!A49 -> Confiabilidad | C4: ='3. Caracterización'!B49 -> ¿Se necesita que el sistema haga copias de respaldo de manera automática, sin que nadie lo solicite? | D4: ='3. Caracterización'!G49 -> 0 | E4: ='3. Caracterización'!H49 -> 0 | F4: ='3. Caracterización'!I49 -> 5 | G4: =SUM(D4:F4) -> 5
A5: 4 | B5: ='3. Caracterización'!A59 -> Disponibilidad | C5: ='3. Caracterización'!B59 -> ¿Se necesita capturar información en el área de cultivo sin ninguna conexión de datos? | D5: ='3. Caracterización'!G59 -> 5 | E5: ='3. Caracterización'!H59 -> 0 | F5: ='3. Caracterización'!I59 -> 0 | G5: =SUM(D5:F5) -> 5
A6: 5 | B6: ='3. Caracterización'!A95 -> Rendimiento | C6: ='3. Caracterización'!B95 -> ¿Se necesita que la proyección se recalcule en el momento en que llega información nueva? | D6: ='3. Caracterización'!G95 -> 0 | E6: ='3. Caracterización'!H95 -> 5 | F6: ='3. Caracterización'!I95 -> 0 | G6: =SUM(D6:F6) -> 5
A7: 6 | B7: ='3. Caracterización'!A162 -> Capacidad para ser Administrado | C7: ='3. Caracterización'!B162 -> ¿Se necesita que quien administra el sistema en la finca no pueda modificar la información de producción? | D7: ='3. Caracterización'!G162 -> 0 | E7: ='3. Caracterización'!H162 -> 0 | F7: ='3. Caracterización'!I162 -> 5 | G7: =SUM(D7:F7) -> 5
A8: 7 | B8: ='3. Caracterización'!A14 -> Confiabilidad | C8: ='3. Caracterización'!B14 -> ¿Se necesita que los rangos y las reglas de validación se puedan cambiar sin depender de una nueva versión de la aplicación? | D8: ='3. Caracterización'!G14 -> 0 | E8: ='3. Caracterización'!H14 -> 3 | F8: ='3. Caracterización'!I14 -> 1 | G8: =SUM(D8:F8) -> 4
A9: 8 | B9: ='3. Caracterización'!A27 -> Confiabilidad | C9: ='3. Caracterización'!B27 -> ¿Se necesita poder corregir un dato ya capturado antes de que se sincronice? | D9: ='3. Caracterización'!G27 -> 4 | E9: ='3. Caracterización'!H27 -> 0 | F9: ='3. Caracterización'!I27 -> 0 | G9: =SUM(D9:F9) -> 4
A10: 9 | B10: ='3. Caracterización'!A35 -> Confiabilidad | C10: ='3. Caracterización'!B35 -> ¿Se necesita saber, sobre cada proyección, con qué datos y con qué parámetros fue calculada? | D10: ='3. Caracterización'!G35 -> 0 | E10: ='3. Caracterización'!H35 -> 4 | F10: ='3. Caracterización'!I35 -> 0 | G10: =SUM(D10:F10) -> 4
A11: 10 | B11: ='3. Caracterización'!A37 -> Confiabilidad | C11: ='3. Caracterización'!B37 -> ¿Se necesita que el sistema muestre cuánto se desvió la proyección anterior frente a lo que realmente se cortó? | D11: ='3. Caracterización'!G37 -> 0 | E11: ='3. Caracterización'!H37 -> 4 | F11: ='3. Caracterización'!I37 -> 0 | G11: =SUM(D11:F11) -> 4
A12: 11 | B12: ='3. Caracterización'!A45 -> Confiabilidad | C12: ='3. Caracterización'!B45 -> ¿Se necesita que la información se conserve cuando el dispositivo se apaga por batería agotada a mitad de una captura? | D12: ='3. Caracterización'!G45 -> 4 | E12: ='3. Caracterización'!H45 -> 0 | F12: ='3. Caracterización'!I45 -> 0 | G12: =SUM(D12:F12) -> 4
A13: 12 | B13: ='3. Caracterización'!A107 -> Capacidad para ser Auditado | C13: ='3. Caracterización'!B107 -> ¿Se necesita poder ver la historia completa de una cama desde la siembra hasta la erradicación? | D13: ='3. Caracterización'!G107 -> 0 | E13: ='3. Caracterización'!H107 -> 4 | F13: ='3. Caracterización'!I107 -> 0 | G13: =SUM(D13:F13) -> 4
A14: 13 | B14: ='3. Caracterización'!A147 -> Capacidad para ser Administrado | C14: ='3. Caracterización'!B147 -> ¿Se necesita poder crear y dar de baja usuarios sin solicitarlo a quien desarrolló el sistema? | D14: ='3. Caracterización'!G147 -> 0 | E14: ='3. Caracterización'!H147 -> 0 | F14: ='3. Caracterización'!I147 -> 4 | G14: =SUM(D14:F14) -> 4
A15: 14 | B15: ='3. Caracterización'!A161 -> Capacidad para ser Administrado | C15: ='3. Caracterización'!B161 -> ¿Se necesita que la administración del sistema se pueda hacer desde un computador de la finca, sin herramientas técnicas especiales? | D15: ='3. Caracterización'!G161 -> 0 | E15: ='3. Caracterización'!H161 -> 0 | F15: ='3. Caracterización'!I161 -> 4 | G15: =SUM(D15:F15) -> 4
A16: 15 | B16: ='3. Caracterización'!A165 -> Experiencia de Usuario | C16: ='3. Caracterización'!B165 -> ¿Se necesita que la pantalla sea legible bajo el sol directo? | D16: ='3. Caracterización'!G165 -> 4 | E16: ='3. Caracterización'!H165 -> 0 | F16: ='3. Caracterización'!I165 -> 0 | G16: =SUM(D16:F16) -> 4
A17: 16 | B17: ='3. Caracterización'!A248 -> Portabilidad | C17: ='3. Caracterización'!B248 -> ¿Se necesita que el sistema pueda instalarse en servidores de la propia empresa y no solo en la nube? | D17: ='3. Caracterización'!G248 -> 0 | E17: ='3. Caracterización'!H248 -> 0 | F17: ='3. Caracterización'!I248 -> 4 | G17: =SUM(D17:F17) -> 4
A18: 17 | B18: ='3. Caracterización'!A19 -> Confiabilidad | C18: ='3. Caracterización'!B19 -> ¿Se necesita que el sistema bloquee la captura cuando detecta que la fecha y la hora del dispositivo fueron alteradas? | D18: ='3. Caracterización'!G19 -> 1 | E18: ='3. Caracterización'!H19 -> 0 | F18: ='3. Caracterización'!I19 -> 2 | G18: =SUM(D18:F18) -> 3
A19: 18 | B19: ='3. Caracterización'!A46 -> Confiabilidad | C19: ='3. Caracterización'!B46 -> ¿Se necesita que la información se conserve cuando la aplicación se cierra de manera inesperada? | D19: ='3. Caracterización'!G46 -> 3 | E19: ='3. Caracterización'!H46 -> 0 | F19: ='3. Caracterización'!I46 -> 0 | G19: =SUM(D19:F19) -> 3
A20: 19 | B20: ='3. Caracterización'!A57 -> Confiabilidad | C20: ='3. Caracterización'!B57 -> ¿Se necesita que exista una prueba periódica de que las copias de respaldo efectivamente sirven? | D20: ='3. Caracterización'!G57 -> 0 | E20: ='3. Caracterización'!H57 -> 0 | F20: ='3. Caracterización'!I57 -> 3 | G20: =SUM(D20:F20) -> 3
A21: 20 | B21: ='3. Caracterización'!A78 -> Disponibilidad | C21: ='3. Caracterización'!B78 -> ¿Se necesita que el sistema avise cuando un dispositivo lleva demasiado tiempo sin sincronizar? | D21: ='3. Caracterización'!G78 -> 3 | E21: ='3. Caracterización'!H78 -> 0 | F21: ='3. Caracterización'!I78 -> 0 | G21: =SUM(D21:F21) -> 3
A22: 21 | B22: ='3. Caracterización'!A145 -> Capacidad | C22: ='3. Caracterización'!B145 -> ¿Se necesita prever un crecimiento del volumen de información año tras año sin cambiar de sistema? | D22: ='3. Caracterización'!G145 -> 0 | E22: ='3. Caracterización'!H145 -> 3 | F22: ='3. Caracterización'!I145 -> 0 | G22: =SUM(D22:F22) -> 3
A23: 22 | B23: ='3. Caracterización'!A148 -> Capacidad para ser Administrado | C23: ='3. Caracterización'!B148 -> ¿Se necesita poder cambiar los permisos de un usuario de manera inmediata? | D23: ='3. Caracterización'!G148 -> 0 | E23: ='3. Caracterización'!H148 -> 0 | F23: ='3. Caracterización'!I148 -> 3 | G23: =SUM(D23:F23) -> 3
A24: 23 | B24: ='3. Caracterización'!A151 -> Capacidad para ser Administrado | C24: ='3. Caracterización'!B151 -> ¿Se necesita poder crear variedades nuevas sin desarrollo adicional? | D24: ='3. Caracterización'!G151 -> 0 | E24: ='3. Caracterización'!H151 -> 3 | F24: ='3. Caracterización'!I151 -> 0 | G24: =SUM(D24:F24) -> 3
A25: 24 | B25: ='3. Caracterización'!A153 -> Capacidad para ser Administrado | C25: ='3. Caracterización'!B153 -> ¿Se necesita poder cambiar la densidad de siembra o los parámetros de cálculo sin desarrollo adicional? | D25: ='3. Caracterización'!G153 -> 0 | E25: ='3. Caracterización'!H153 -> 3 | F25: ='3. Caracterización'!I153 -> 0 | G25: =SUM(D25:F25) -> 3
A26: 25 | B26: ='3. Caracterización'!A158 -> Capacidad para ser Administrado | C26: ='3. Caracterización'!B158 -> ¿Se necesita poder actualizar la aplicación en todos los dispositivos sin recogerlos uno por uno? | D26: ='3. Caracterización'!G158 -> 0 | E26: ='3. Caracterización'!H158 -> 0 | F26: ='3. Caracterización'!I158 -> 3 | G26: =SUM(D26:F26) -> 3
A27: 26 | B27: ='3. Caracterización'!A167 -> Experiencia de Usuario | C27: ='3. Caracterización'!B167 -> ¿Se necesita reducir al mínimo la cantidad de toques necesarios para registrar una cama? | D27: ='3. Caracterización'!G167 -> 3 | E27: ='3. Caracterización'!H167 -> 0 | F27: ='3. Caracterización'!I167 -> 0 | G27: =SUM(D27:F27) -> 3
A28: 27 | B28: ='3. Caracterización'!A174 -> Experiencia de Usuario | C28: ='3. Caracterización'!B174 -> ¿Se necesita poder identificar la cama escaneando una marca física en lugar de escribir el código? | D28: ='3. Caracterización'!G174 -> 3 | E28: ='3. Caracterización'!H174 -> 0 | F28: ='3. Caracterización'!I174 -> 0 | G28: =SUM(D28:F28) -> 3
A29: 28 | B29: ='3. Caracterización'!A183 -> Seguridad | C29: ='3. Caracterización'!B183 -> ¿Se necesita que la sesión se cierre sola después de un tiempo sin uso? | D29: ='3. Caracterización'!G183 -> 0 | E29: ='3. Caracterización'!H183 -> 0 | F29: ='3. Caracterización'!I183 -> 3 | G29: =SUM(D29:F29) -> 3
A30: 29 | B30: ='3. Caracterización'!A209 -> Interoperatividad | C30: ='3. Caracterización'!B209 -> ¿Se necesita que la información se pueda leer desde una herramienta de análisis externa? | D30: ='3. Caracterización'!G209 -> 0 | E30: ='3. Caracterización'!H209 -> 3 | F30: ='3. Caracterización'!I209 -> 0 | G30: =SUM(D30:F30) -> 3
A31: 30 | B31: ='3. Caracterización'!A229 -> Capacidad para ser Soportado | C31: ='3. Caracterización'!B229 -> ¿Se necesita poder diagnosticar un problema sin tener que desplazarse hasta la finca? | D31: ='3. Caracterización'!G229 -> 0 | E31: ='3. Caracterización'!H229 -> 0 | F31: ='3. Caracterización'!I229 -> 3 | G31: =SUM(D31:F31) -> 3
A32: 31 | B32: ='3. Caracterización'!A230 -> Capacidad para ser Soportado | C32: ='3. Caracterización'!B230 -> ¿Se necesita poder revisar el estado de un dispositivo de forma remota? | D32: ='3. Caracterización'!G230 -> 0 | E32: ='3. Caracterización'!H230 -> 0 | F32: ='3. Caracterización'!I230 -> 3 | G32: =SUM(D32:F32) -> 3
A33: 32 | B33: ='3. Caracterización'!A237 -> Portabilidad | C33: ='3. Caracterización'!B237 -> ¿Se necesita que la aplicación de captura funcione en dispositivos Android? | D33: ='3. Caracterización'!G237 -> 3 | E33: ='3. Caracterización'!H237 -> 0 | F33: ='3. Caracterización'!I237 -> 0 | G33: =SUM(D33:F33) -> 3
A34: 33 | B34: ='3. Caracterización'!A7 -> Confiabilidad | C34: ='3. Caracterización'!B7 -> ¿Se necesita verificar que la información sea correcta de manera que se agrupe la información por finca y por jornada completa? | D34: ='3. Caracterización'!G7 -> 0 | E34: ='3. Caracterización'!H7 -> 2 | F34: ='3. Caracterización'!I7 -> 0 | G34: =SUM(D34:F34) -> 2
A35: 34 | B35: ='3. Caracterización'!A16 -> Confiabilidad | C35: ='3. Caracterización'!B16 -> ¿Se necesita que el sistema avise cuando se intenta capturar dos veces la misma cama el mismo día? | D35: ='3. Caracterización'!G16 -> 2 | E35: ='3. Caracterización'!H16 -> 0 | F35: ='3. Caracterización'!I16 -> 0 | G35: =SUM(D35:F35) -> 2
A36: 35 | B36: ='3. Caracterización'!A58 -> Confiabilidad | C36: ='3. Caracterización'!B58 -> ¿Se necesita que la aplicación avise cuando el almacenamiento del dispositivo está por llenarse? | D36: ='3. Caracterización'!G58 -> 2 | E36: ='3. Caracterización'!H58 -> 0 | F36: ='3. Caracterización'!I58 -> 0 | G36: =SUM(D36:F36) -> 2
A37: 36 | B37: ='3. Caracterización'!A84 -> Rendimiento | C37: ='3. Caracterización'!B84 -> ¿Se necesita que cada dato quede guardado de inmediato, sin espera perceptible? | D37: ='3. Caracterización'!G84 -> 2 | E37: ='3. Caracterización'!H84 -> 0 | F37: ='3. Caracterización'!I84 -> 0 | G37: =SUM(D37:F37) -> 2
A38: 37 | B38: ='3. Caracterización'!A85 -> Rendimiento | C38: ='3. Caracterización'!B85 -> ¿Se necesita que el paso de una pantalla a la siguiente sea inmediato aun sin conexión? | D38: ='3. Caracterización'!G85 -> 2 | E38: ='3. Caracterización'!H85 -> 0 | F38: ='3. Caracterización'!I85 -> 0 | G38: =SUM(D38:F38) -> 2
A39: 38 | B39: ='3. Caracterización'!A89 -> Rendimiento | C39: ='3. Caracterización'!B89 -> ¿Se necesita que muchos dispositivos puedan sincronizar al mismo tiempo al terminar la jornada sin que el sistema se degrade? | D39: ='3. Caracterización'!G89 -> 1 | E39: ='3. Caracterización'!H89 -> 0 | F39: ='3. Caracterización'!I89 -> 1 | G39: =SUM(D39:F39) -> 2
A40: 39 | B40: ='3. Caracterización'!A110 -> Capacidad para ser Auditado | C40: ='3. Caracterización'!B110 -> ¿Se necesita poder llegar, desde una cifra de un reporte, hasta los datos individuales que la componen? | D40: ='3. Caracterización'!G110 -> 0 | E40: ='3. Caracterización'!H110 -> 2 | F40: ='3. Caracterización'!I110 -> 0 | G40: =SUM(D40:F40) -> 2
A41: 40 | B41: ='3. Caracterización'!A112 -> Capacidad para ser Auditado | C41: ='3. Caracterización'!B112 -> ¿Se necesita que el registro de lo ocurrido no pueda ser alterado ni borrado por nadie? | D41: ='3. Caracterización'!G112 -> 0 | E41: ='3. Caracterización'!H112 -> 0 | F41: ='3. Caracterización'!I112 -> 2 | G41: =SUM(D41:F41) -> 2
A42: 41 | B42: ='3. Caracterización'!A136 -> Capacidad | C42: ='3. Caracterización'!B136 -> ¿Se necesita conservar en línea la información de los últimos cinco años? | D42: ='3. Caracterización'!G136 -> 0 | E42: ='3. Caracterización'!H136 -> 2 | F42: ='3. Caracterización'!I136 -> 0 | G42: =SUM(D42:F42) -> 2
A43: 42 | B43: ='3. Caracterización'!A139 -> Capacidad | C43: ='3. Caracterización'!B139 -> ¿Se aceptaría que la información de más de cierta antigüedad tarde más en consultarse? | D43: ='3. Caracterización'!G139 -> 0 | E43: ='3. Caracterización'!H139 -> 2 | F43: ='3. Caracterización'!I139 -> 0 | G43: =SUM(D43:F43) -> 2
A44: 43 | B44: ='3. Caracterización'!A146 -> Capacidad | C44: ='3. Caracterización'!B146 -> ¿Se necesita que el costo de almacenamiento por finca se mantenga acotado a medida que crece la historia? | D44: ='3. Caracterización'!G146 -> 0 | E44: ='3. Caracterización'!H146 -> 1 | F44: ='3. Caracterización'!I146 -> 1 | G44: =SUM(D44:F44) -> 2
A45: 44 | B45: ='3. Caracterización'!A152 -> Capacidad para ser Administrado | C45: ='3. Caracterización'!B152 -> ¿Se necesita poder cambiar los grados de calidad y sus definiciones sin desarrollo adicional? | D45: ='3. Caracterización'!G152 -> 0 | E45: ='3. Caracterización'!H152 -> 2 | F45: ='3. Caracterización'!I152 -> 0 | G45: =SUM(D45:F45) -> 2
A46: 45 | B46: ='3. Caracterización'!A154 -> Capacidad para ser Administrado | C46: ='3. Caracterización'!B154 -> ¿Se necesita que un cambio de parámetros no altere las proyecciones ya emitidas? | D46: ='3. Caracterización'!G154 -> 0 | E46: ='3. Caracterización'!H154 -> 2 | F46: ='3. Caracterización'!I154 -> 0 | G46: =SUM(D46:F46) -> 2
A47: 46 | B47: ='3. Caracterización'!A157 -> Capacidad para ser Administrado | C47: ='3. Caracterización'!B157 -> ¿Se necesita poder forzar la sincronización de un dispositivo de manera remota? | D47: ='3. Caracterización'!G157 -> 0 | E47: ='3. Caracterización'!H157 -> 0 | F47: ='3. Caracterización'!I157 -> 2 | G47: =SUM(D47:F47) -> 2
A48: 47 | B48: ='3. Caracterización'!A170 -> Experiencia de Usuario | C48: ='3. Caracterización'!B170 -> ¿Se necesita que la aplicación indique con claridad qué información ya se sincronizó y cuál no? | D48: ='3. Caracterización'!G170 -> 2 | E48: ='3. Caracterización'!H170 -> 0 | F48: ='3. Caracterización'!I170 -> 0 | G48: =SUM(D48:F48) -> 2
A49: 48 | B49: ='3. Caracterización'!A171 -> Experiencia de Usuario | C49: ='3. Caracterización'!B171 -> ¿Se necesita que los nombres que aparecen en pantalla sean exactamente los que se usan hablando en la finca? | D49: ='3. Caracterización'!G171 -> 2 | E49: ='3. Caracterización'!H171 -> 0 | F49: ='3. Caracterización'!I171 -> 0 | G49: =SUM(D49:F49) -> 2
A50: 49 | B50: ='3. Caracterización'!A181 -> Seguridad | C50: ='3. Caracterización'!B181 -> ¿Se necesita que cada persona entre al sistema con una identificación propia y no compartida? | D50: ='3. Caracterización'!G181 -> 0 | E50: ='3. Caracterización'!H181 -> 0 | F50: ='3. Caracterización'!I181 -> 2 | G50: =SUM(D50:F50) -> 2
A51: 50 | B51: ='3. Caracterización'!A188 -> Seguridad | C51: ='3. Caracterización'!B188 -> ¿Se necesita que quien opera la plataforma no pueda leer la información de producción de la empresa? | D51: ='3. Caracterización'!G188 -> 0 | E51: ='3. Caracterización'!H188 -> 0 | F51: ='3. Caracterización'!I188 -> 2 | G51: =SUM(D51:F51) -> 2
A52: 51 | B52: ='3. Caracterización'!A200 -> Interoperatividad | C52: ='3. Caracterización'!B200 -> ¿Se necesita poder exportar la información a Excel? | D52: ='3. Caracterización'!G200 -> 0 | E52: ='3. Caracterización'!H200 -> 2 | F52: ='3. Caracterización'!I200 -> 0 | G52: =SUM(D52:F52) -> 2
A53: 52 | B53: ='3. Caracterización'!A215 -> Escalabilidad | C53: ='3. Caracterización'!B215 -> ¿Se necesita poder agregar una finca nueva sin volver a instalar ni reconfigurar todo? | D53: ='3. Caracterización'!G215 -> 0 | E53: ='3. Caracterización'!H215 -> 0 | F53: ='3. Caracterización'!I215 -> 2 | G53: =SUM(D53:F53) -> 2
A54: 53 | B54: ='3. Caracterización'!A224 -> Capacidad para ser Soportado | C54: ='3. Caracterización'!B224 -> ¿Se necesita que exista alguien dentro de la finca capaz de resolver los problemas del día a día? | D54: ='3. Caracterización'!G224 -> 0 | E54: ='3. Caracterización'!H224 -> 0 | F54: ='3. Caracterización'!I224 -> 2 | G54: =SUM(D54:F54) -> 2
A55: 54 | B55: ='3. Caracterización'!A242 -> Portabilidad | C55: ='3. Caracterización'!B242 -> ¿Se necesita poder cambiar de dispositivo conservando la información que aún no se ha sincronizado? | D55: ='3. Caracterización'!G242 -> 2 | E55: ='3. Caracterización'!H242 -> 0 | F55: ='3. Caracterización'!I242 -> 0 | G55: =SUM(D55:F55) -> 2
A56: 55 | B56: ='3. Caracterización'!A10 -> Confiabilidad | C56: ='3. Caracterización'!B10 -> ¿Se necesita que el sistema permita guardar una captura incompleta y marcarla como pendiente? | D56: ='3. Caracterización'!G10 -> 0 | E56: ='3. Caracterización'!H10 -> 1 | F56: ='3. Caracterización'!I10 -> 0 | G56: =SUM(D56:F56) -> 1
A57: 56 | B57: ='3. Caracterización'!A13 -> Confiabilidad | C57: ='3. Caracterización'!B13 -> ¿Se necesita que el sistema muestre siempre el motivo por el cual rechazó un dato? | D57: ='3. Caracterización'!G13 -> 0 | E57: ='3. Caracterización'!H13 -> 1 | F57: ='3. Caracterización'!I13 -> 0 | G57: =SUM(D57:F57) -> 1
A58: 57 | B58: ='3. Caracterización'!A15 -> Confiabilidad | C58: ='3. Caracterización'!B15 -> ¿Se necesita que las reglas de validación funcionen igual estando sin conexión que estando conectado? | D58: ='3. Caracterización'!G15 -> 1 | E58: ='3. Caracterización'!H15 -> 0 | F58: ='3. Caracterización'!I15 -> 0 | G58: =SUM(D58:F58) -> 1
A59: 58 | B59: ='3. Caracterización'!A28 -> Confiabilidad | C59: ='3. Caracterización'!B28 -> ¿Se necesita poder corregir un dato después de que se sincronizó? | D59: ='3. Caracterización'!G28 -> 0 | E59: ='3. Caracterización'!H28 -> 0 | F59: ='3. Caracterización'!I28 -> 1 | G59: =SUM(D59:F59) -> 1
A60: 59 | B60: ='3. Caracterización'!A66 -> Disponibilidad | C60: ='3. Caracterización'!B66 -> ¿Se necesita que la captura siga funcionando aunque el servicio en la nube esté caído? | D60: ='3. Caracterización'!G66 -> 1 | E60: ='3. Caracterización'!H66 -> 0 | F60: ='3. Caracterización'!I66 -> 0 | G60: =SUM(D60:F60) -> 1
A61: 60 | B61: ='3. Caracterización'!A91 -> Rendimiento | C61: ='3. Caracterización'!B91 -> ¿Se necesita que la información sincronizada se vea reflejada en la consulta web dentro de la misma hora? | D61: ='3. Caracterización'!G91 -> 0 | E61: ='3. Caracterización'!H91 -> 1 | F61: ='3. Caracterización'!I91 -> 0 | G61: =SUM(D61:F61) -> 1
A62: 61 | B62: ='3. Caracterización'!A99 -> Rendimiento | C62: ='3. Caracterización'!B99 -> ¿Se necesita que el rendimiento se mantenga igual en temporada alta que en el resto del año? | D62: ='3. Caracterización'!G99 -> 0 | E62: ='3. Caracterización'!H99 -> 1 | F62: ='3. Caracterización'!I99 -> 0 | G62: =SUM(D62:F62) -> 1
A63: 62 | B63: ='3. Caracterización'!A108 -> Capacidad para ser Auditado | C63: ='3. Caracterización'!B108 -> ¿Se necesita poder ver la historia completa de un lote a través de varias camas? | D63: ='3. Caracterización'!G108 -> 0 | E63: ='3. Caracterización'!H108 -> 1 | F63: ='3. Caracterización'!I108 -> 0 | G63: =SUM(D63:F63) -> 1
A64: 63 | B64: ='3. Caracterización'!A116 -> Capacidad para ser Auditado | C64: ='3. Caracterización'!B116 -> ¿Se necesita registrar el motivo cada vez que disminuye la cantidad de plantas o de tallos esperados? | D64: ='3. Caracterización'!G116 -> 0 | E64: ='3. Caracterización'!H116 -> 1 | F64: ='3. Caracterización'!I116 -> 0 | G64: =SUM(D64:F64) -> 1
A65: 64 | B65: ='3. Caracterización'!A133 -> Capacidad | C65: ='3. Caracterización'!B133 -> ¿Se necesita que el sistema soporte varias fincas de la misma empresa? | D65: ='3. Caracterización'!G133 -> 0 | E65: ='3. Caracterización'!H133 -> 1 | F65: ='3. Caracterización'!I133 -> 0 | G65: =SUM(D65:F65) -> 1
A66: 65 | B66: ='3. Caracterización'!A144 -> Capacidad | C66: ='3. Caracterización'!B144 -> ¿Se necesita que el dispositivo tenga descargado todo el catálogo de la finca antes de salir a capturar? | D66: ='3. Caracterización'!G144 -> 0 | E66: ='3. Caracterización'!H144 -> 0 | F66: ='3. Caracterización'!I144 -> 1 | G66: =SUM(D66:F66) -> 1
A68: Metodologia: cada rol (Tomador de datos, Producción, Administrador) distribuyó 65 puntos entre 29 preguntas (2x5 + 3x4 + 6x3 + 7x2 + 11x1), priorizando segun la importancia de cada atributo de calidad para ese rol (hoja '2. Priorización-QA'), el consenso de necesidad (SI) en la hoja '3. Caracterización' y las citas textuales del cliente (CITAS_TEXTUALES_CLIENTE.md, HOJA_SESION_CLIENTE.md). Estas son las 65 preguntas con mayor puntaje total sumando los 3 roles; en caso de empate se prefirió el atributo de calidad de mayor prioridad promedio entre los 3 roles, el mayor consenso (SI) entre Juan, Jerónimo y el Cliente, y evidencia textual directa del cliente cuando existía (p. ej. RF-C17 sobre quién corrige un dato ya sincronizado).
