Workbook

Sheet Como leer
A3: Version | B3: 1.0 - PROPUESTA DEL EQUIPO, sin validar con el cliente
A4: Que es | B4: Las opciones tecnologicas concretas para cada bloque de los cuatro nodos, con lo que cada una ES (servicio, contenedor, ejecutable, libreria, API...), su licencia, donde corre y su madurez.
A5: Que NO es | B5: No es una eleccion. Las marcadas con estrella son las que mejor resisten las restricciones del proyecto, no una decision tomada.
A6: De donde sale | B6: FlorLogic_Bloques_Arquitectonicos.xlsx y los cuatro modelos de nodo (MODELO_COMPONENTES / N2 / N3+resumen / N4) + DRIVERS_ARQUITECTONICOS.md
A8: COMO SE LEE LA COLUMNA ESTADO
A9: * Candidata fuerte | B9: Resiste bien las restricciones ya cerradas del proyecto. Verde.
A10: Candidata | B10: Viable, con una contrapartida que la nota explica. Amarillo.
A11: Descartada | B11: Queda fuera por una restriccion concreta, no por gusto. La nota dice cual. Gris.
A13: LOS CUATRO FILTROS QUE MAS DESCARTAN
A14: CN-17 / CN-13 sin red en campo | B14: Descarta todo servicio que exija estar en linea para autenticar, validar o guardar.
A15: CN-37 local-first | B15: Descarta serverless, bases gestionadas y todo lo que solo exista como servicio de nube.
A16: CN-35 costo acotado | B16: Descarta licencias y servicios cuyo precio escale por empresa, usuario o dispositivo.
A17: CN-28 llave del cliente | B17: Descarta el KMS del proveedor de nube y cualquier servicio que necesite leer el contenido.
A19: OJO CON LAS LICENCIAS | B19: Varias candidatas fuertes son AGPL o SSPL (Grafana, MinIO, Loki, Metabase) o BUSL (Vault). Eso no las descarta, pero condiciona redistribuirlas dentro del paquete que se instala en casa del cliente. Revisar antes de fijar el stack.
A21: LO QUE ESTE ARCHIVO NO PUEDE DECIDIR | B21: Tres decisiones siguen abiertas y ninguna se cierra escogiendo tecnologia: T1 (PWA o nativa, atada a A5 y CN-21), T2 (que es fisicamente el nodo de finca, atada a CN-20) y la decision 5 (donde corre el modelo de IA).

Sheet Catalogo de tecnologias
A1: Nodo | B1: Bloque Arquitectónico | C1: Tecnología | D1: Qué es | E1: Licencia y modelo de costo | F1: Dónde corre y forma de despliegue | G1: Madurez y riesgo de mantenimiento | H1: Estado | I1: Por qué — nota
A2: N1 | B2: Almacenamiento Dedicado a Capturas · cola de salida | C2: SQLite (con SQLCipher) | D2: Motor de base de datos embebido | E2: Dominio público / BSD | F2: Archivo dentro del área privada de la app | G2: Máxima. Transaccional, sobrevive a cierres inesperados | H2: ★ Candidata fuerte | I2: ESC-18 pide sobrevivir al cierre inesperado con un campo por rehacer como máximo: eso es una transacción, y SQLite la da
A3: N1 | B3: Almacenamiento Dedicado a Capturas · cola de salida | C3: IndexedDB (lo actual) | D3: API de almacenamiento del navegador | E3: Sin costo | F3: Navegador del dispositivo | G3: Funciona, pero con el riesgo de desalojo ya descrito | H3: Candidata | I3: Sostenible mientras el dispositivo sea Android y la app esté instalada como PWA. Se cae si entra iOS
A4: N1 | B4: Almacenamiento Dedicado a Capturas · cola de salida | C4: Realm · ObjectBox | D4: Base de datos embebida orientada a objetos, con sincronización propia | E4: Apache 2.0 el núcleo. El servicio de sincronización es comercial | F4: Librería en la app | G4: Alta | H4: Descartada | I4: Traen su propio motor de sincronización, y RF-022 fija una regla concreta —gana el más reciente, sin mediación— que no conviene delegar en la política de un tercero
A5: N1 | B5: App Captura · framework de aplicación móvil | C5: PWA propia sin dependencias (lo ya construido) | D5: Aplicación web instalable. Código propio, sin framework ni árbol npm | E5: Sin costo. Cero dependencias de terceros | F5: Navegador del Android. Se sirve como archivos estáticos desde el nodo de finca | G5: Ya construida y verificada con seis suites de prueba. El riesgo es del equipo, no de un tercero | H5: ★ Candidata fuerte | I5: Es lo único que ya existe y funciona. Límite conocido: con WebCrypto la llave queda en IndexedDB y el cifrado en reposo no se puede demostrar (tensiona A5)
A6: N1 | B6: App Captura · framework de aplicación móvil | C6: Flutter | D6: SDK multiplataforma en Dart. Compila a binario nativo | E6: BSD-3. Sin costo ni licencias por dispositivo | F6: APK instalado en el dispositivo | G6: Muy alta, respaldada por Google. Curva de aprendizaje real: Juan lo exploró sin dominarlo | H6: ★ Candidata fuerte | I6: Resuelve el cifrado en reposo demostrable y el desalojo de IndexedDB en iOS. Es la salida natural si A5 se sostiene
A7: N1 | B7: App Captura · framework de aplicación móvil | C7: Android nativo · Kotlin + Jetpack Compose | D7: SDK y lenguaje nativo de la plataforma | E7: Apache 2.0. Sin costo | F7: APK instalado en el dispositivo | G7: Altísima. Acceso completo a Keystore, SQLCipher y APIs de reloj | H7: ★ Candidata fuerte | I7: El máximo control sobre cifrado, almacenamiento y detección de reloj alterado. Solo Android — y ESC-32 pide Android
A8: N1 | B8: App Captura · framework de aplicación móvil | C8: Ionic + Capacitor | D8: Envoltorio nativo sobre una aplicación web | E8: MIT. Sin costo | F8: APK que embebe la vista web y expone APIs nativas | G8: Alta y estable. Comunidad amplia | H8: Candidata | I8: Es el puente más barato entre la PWA ya escrita y lo que A5 exige: conserva el código y gana acceso nativo a cifrado y almacenamiento
A9: N1 | B9: App Captura · framework de aplicación móvil | C9: .NET MAUI | D9: SDK multiplataforma de Microsoft | E9: MIT. Sin costo | F9: APK con runtime .NET | G9: Media. Comunidad menor que Flutter y menos ejemplos offline-first | H9: Candidata | I9: Solo tiene sentido si el backend termina siendo .NET y se quiere un único lenguaje para los dos
A10: N1 | B10: App Captura · framework de aplicación móvil | C10: React Native | D10: Framework JavaScript con puente nativo | E10: MIT. Sin costo | F10: APK con runtime JS y dependencias npm | G10: Alta, pero con árbol de dependencias grande y actualizaciones frecuentes | H10: Descartada | I10: La demo se construyó con cero dependencias porque cada «npm install» es un punto de fallo donde la app tiene que funcionar. No aporta nada sobre Flutter
A11: N1 | B11: Business Layer · orquestador local | C11: Código propio dentro de la app | D11: Capa de aplicación escrita a mano, sin marco | E11: Sin costo | F11: Dentro del proceso de la app de captura | G11: Depende del equipo. Es el corazón de N1: valida, decide y guarda | H11: ★ Candidata fuerte | I11: No hay librería que resuelva esto: la lógica de «validar antes de guardar» es específica del dominio. Lo que sí conviene es un patrón claro (casos de uso) para que Juan y Jerónimo escriban igual
A12: N1 | B12: Business Layer · orquestador local | C12: Riverpod / Bloc (si Flutter) | D12: Librería de gestión de estado y flujo de la aplicación | E12: MIT / BSD. Sin costo | F12: Embebida en la app | G12: Alta. Son el estándar de facto en Flutter | H12: Candidata | I12: No sustituye la lógica, la organiza. Útil para que el estado de la captura no quede desperdigado por la interfaz
... A141: N4 | B141: Servicio de IA analítica | C141: Modelo pequeño en el propio dispositivo | D141: Pesos embebidos en la app | E141: Varía | F141: Dispositivo Android | G141: Media. Los modelos pequeños son limitados | H141: Candidata | I141: Aplica al asistente de captura de C2, no a la IA analítica. Es la otra mitad de la decisión 5

Sheet Resumen por bloque
A1: Nodo | B1: Bloque Arquitectónico | C1: Candidatas fuertes | D1: Candidatas | E1: Descartadas | F1: Total
A2: N1 | B2: Almacenamiento Dedicado a Capturas · cola de salida | C2: =COUNTIFS('Catalogo de tecnologias'!$B:$B,$B2,'Catalogo de tecnologias'!$H:$H,"★ Candidata fuerte") -> 1 | D2: =COUNTIFS('Catalogo de tecnologias'!$B:$B,$B2,'Catalogo de tecnologias'!$H:$H,"Candidata") -> 1 | E2: =COUNTIFS('Catalogo de tecnologias'!$B:$B,$B2,'Catalogo de tecnologias'!$H:$H,"Descartada") -> 1 | F2: =SUM(C2:E2) -> 3
A3: N1 | B3: App Captura · framework de aplicación móvil | C3: =COUNTIFS('Catalogo de tecnologias'!$B:$B,$B3,'Catalogo de tecnologias'!$H:$H,"★ Candidata fuerte") -> 3 | D3: =COUNTIFS('Catalogo de tecnologias'!$B:$B,$B3,'Catalogo de tecnologias'!$H:$H,"Candidata") -> 2 | E3: =COUNTIFS('Catalogo de tecnologias'!$B:$B,$B3,'Catalogo de tecnologias'!$H:$H,"Descartada") -> 1 | F3: =SUM(C3:E3) -> 6
A4: N1 | B4: Business Layer · orquestador local | C4: =COUNTIFS('Catalogo de tecnologias'!$B:$B,$B4,'Catalogo de tecnologias'!$H:$H,"★ Candidata fuerte") -> 1 | D4: =COUNTIFS('Catalogo de tecnologias'!$B:$B,$B4,'Catalogo de tecnologias'!$H:$H,"Candidata") -> 1 | E4: =COUNTIFS('Catalogo de tecnologias'!$B:$B,$B4,'Catalogo de tecnologias'!$H:$H,"Descartada") -> 0 | F4: =SUM(C4:E4) -> 2
A5: N1 | B5: Captura de identificador físico · QR | C5: =COUNTIFS('Catalogo de tecnologias'!$B:$B,$B5,'Catalogo de tecnologias'!$H:$H,"★ Candidata fuerte") -> 1 | D5: =COUNTIFS('Catalogo de tecnologias'!$B:$B,$B5,'Catalogo de tecnologias'!$H:$H,"Candidata") -> 1 | E5: =COUNTIFS('Catalogo de tecnologias'!$B:$B,$B5,'Catalogo de tecnologias'!$H:$H,"Descartada") -> 0 | F5: =SUM(C5:E5) -> 2
A6: N1 | B6: Configuración Local reciente · almacén del paquete versionado | C6: =COUNTIFS('Catalogo de tecnologias'!$B:$B,$B6,'Catalogo de tecnologias'!$H:$H,"★ Candidata fuerte") -> 1 | D6: =COUNTIFS('Catalogo de tecnologias'!$B:$B,$B6,'Catalogo de tecnologias'!$H:$H,"Candidata") -> 2 | E6: =COUNTIFS('Catalogo de tecnologias'!$B:$B,$B6,'Catalogo de tecnologias'!$H:$H,"Descartada") -> 0 | F6: =SUM(C6:E6) -> 3
A7: N1 | B7: Motor de reglas · instancia local | C7: =COUNTIFS('Catalogo de tecnologias'!$B:$B,$B7,'Catalogo de tecnologias'!$H:$H,"★ Candidata fuerte") -> 1 | D7: =COUNTIFS('Catalogo de tecnologias'!$B:$B,$B7,'Catalogo de tecnologias'!$H:$H,"Candidata") -> 2 | E7: =COUNTIFS('Catalogo de tecnologias'!$B:$B,$B7,'Catalogo de tecnologias'!$H:$H,"Descartada") -> 1 | F7: =SUM(C7:E7) -> 4
A8: N1 | B8: Servicio de Cifrado del dispositivo | C8: =COUNTIFS('Catalogo de tecnologias'!$B:$B,$B8,'Catalogo de tecnologias'!$H:$H,"★ Candidata fuerte") -> 1 | D8: =COUNTIFS('Catalogo de tecnologias'!$B:$B,$B8,'Catalogo de tecnologias'!$H:$H,"Candidata") -> 1 | E8: =COUNTIFS('Catalogo de tecnologias'!$B:$B,$B8,'Catalogo de tecnologias'!$H:$H,"Descartada") -> 0 | F8: =SUM(C8:E8) -> 2
A9: N1 | B9: Servicio de sincronización · cliente | C9: =COUNTIFS('Catalogo de tecnologias'!$B:$B,$B9,'Catalogo de tecnologias'!$H:$H,"★ Candidata fuerte") -> 1 | D9: =COUNTIFS('Catalogo de tecnologias'!$B:$B,$B9,'Catalogo de tecnologias'!$H:$H,"Candidata") -> 3 | E9: =COUNTIFS('Catalogo de tecnologias'!$B:$B,$B9,'Catalogo de tecnologias'!$H:$H,"Descartada") -> 1 | F9: =SUM(C9:E9) -> 5
A10: N1 | B10: Verificación de permisos · IAM offline | C10: =COUNTIFS('Catalogo de tecnologias'!$B:$B,$B10,'Catalogo de tecnologias'!$H:$H,"★ Candidata fuerte") -> 1 | D10: =COUNTIFS('Catalogo de tecnologias'!$B:$B,$B10,'Catalogo de tecnologias'!$H:$H,"Candidata") -> 0 | E10: =COUNTIFS('Catalogo de tecnologias'!$B:$B,$B10,'Catalogo de tecnologias'!$H:$H,"Descartada") -> 1 | F10: =SUM(C10:E10) -> 2
A11: N2 | B11: API Gateway & WAF | C11: =COUNTIFS('Catalogo de tecnologias'!$B:$B,$B11,'Catalogo de tecnologias'!$H:$H,"★ Candidata fuerte") -> 2 | D11: =COUNTIFS('Catalogo de tecnologias'!$B:$B,$B11,'Catalogo de tecnologias'!$H:$H,"Candidata") -> 2 | E11: =COUNTIFS('Catalogo de tecnologias'!$B:$B,$B11,'Catalogo de tecnologias'!$H:$H,"Descartada") -> 1 | F11: =SUM(C11:E11) -> 5
A12: N2 | B12: Archivo Histórico | C12: =COUNTIFS('Catalogo de tecnologias'!$B:$B,$B12,'Catalogo de tecnologias'!$H:$H,"★ Candidata fuerte") -> 1 | D12: =COUNTIFS('Catalogo de tecnologias'!$B:$B,$B12,'Catalogo de tecnologias'!$H:$H,"Candidata") -> 1 | E12: =COUNTIFS('Catalogo de tecnologias'!$B:$B,$B12,'Catalogo de tecnologias'!$H:$H,"Descartada") -> 0 | F12: =SUM(C12:E12) -> 2
A13: N2 | B13: Base de Datos principal | C13: =COUNTIFS('Catalogo de tecnologias'!$B:$B,$B13,'Catalogo de tecnologias'!$H:$H,"★ Candidata fuerte") -> 1 | D13: =COUNTIFS('Catalogo de tecnologias'!$B:$B,$B13,'Catalogo de tecnologias'!$H:$H,"Candidata") -> 3 | E13: =COUNTIFS('Catalogo de tecnologias'!$B:$B,$B13,'Catalogo de tecnologias'!$H:$H,"Descartada") -> 1 | F13: =SUM(C13:E13) -> 5
... A50: N4 | B50: Servicio de IA analítica | C50: =COUNTIFS('Catalogo de tecnologias'!$B:$B,$B50,'Catalogo de tecnologias'!$H:$H,"★ Candidata fuerte") -> 1 | D50: =COUNTIFS('Catalogo de tecnologias'!$B:$B,$B50,'Catalogo de tecnologias'!$H:$H,"Candidata") -> 2 | E50: =COUNTIFS('Catalogo de tecnologias'!$B:$B,$B50,'Catalogo de tecnologias'!$H:$H,"Descartada") -> 1 | F50: =SUM(C50:E50) -> 4
B51: TOTAL | C51: =SUM(C2:C50) -> 60 | D51: =SUM(D2:D50) -> 57 | E51: =SUM(E2:E50) -> 23 | F51: =SUM(F2:F50) -> 140
