Workbook

Sheet Como leer
A1: FlorLogic - Requisitos funcionales criticos, v1
A2: Entrega parcial y deliberadamente incompleta. Solo cubre funcionalidades criticas, para poder derivar atributos de calidad y escenarios. 8 de agosto de 2026.
A4: Que es esto | B4: Un primer corte del catalogo de requisitos funcionales, limitado a lo critico. No es el catalogo completo ni pretende serlo: es el subconjunto que basta para empezar a plantear atributos de calidad y escenarios de calidad.
A5: Que NO es esto | B5: No cubre reportes secundarios, exportaciones, gestion de usuarios rutinaria, ni nada fuera del alcance de fase 1 (cruce con pedidos y clientes, Florverde, personal e insumos, actividades culturales obligatorias).
A6: Criterio de criticidad | B6: Cuatro ejes, cada uno de 0 a 3: (1) sin esto no hay producto, (2) riesgo arquitectonico, (3) impacto de negocio, (4) riesgo de fallo. La hoja 'Criticidad' calcula el indice ponderado con pesos editables.
A7: Convenciones | B7: Un requisito = una capacidad. Verbo observable (registrar, calcular, mostrar, impedir, sincronizar). Sin solucion tecnica en el enunciado. Criterio de aceptacion en Dado/Cuando/Entonces. Prioridad MoSCoW.
A8: Codigo de color | B8: Verde: confirmado por el cliente en sesion. Amarillo: parcial o inferido, falta confirmar. Naranja: apoyado en una brecha abierta que puede invalidarlo.
A9: De donde sale | B9: Sesion 1 (27-jul-2026), sesion 2 (4-ago-2026) y el documento de contexto v2.0. Las citas son del Director de Produccion salvo indicacion contraria.
A10: Advertencia de una sola fuente | B10: Todo descansa en un unico entrevistado. Planeacion, que es donde nace la proyeccion, nunca se exploro. Es un riesgo aceptado, no resuelto.
A11: Siguiente paso | B11: Con los RF de indice mas alto, escribir los escenarios de calidad en formato fuente / estimulo / artefacto / entorno / respuesta / medida de respuesta. La hoja 'Mapa de calidad' deja preparado el insumo.

Sheet RF Criticos
A1: Catalogo de requisitos funcionales criticos
A2: Ordenado por modulo. El indice de criticidad se calcula en la hoja 'Criticidad'.
A4: ID | B4: Modulo | C4: Requisito | D4: Actor / Rol | E4: Regla de negocio asociada | F4: Criterio de aceptacion (Dado / Cuando / Entonces) | G4: Origen | H4: Prio. MoSCoW | I4: Indice criticidad | J4: Estado
A5: RF-C01 | B5: Captura en campo | C5: El sistema debe permitir registrar la siembra de una cama (bloque, nave, cama, variedad, fecha, cantidad de esquejes) sin conexion a internet, y confirmar al usuario que el registro quedo guardado. | D5: Supervisor de campo | E5: RN-01: la captura en campo no puede depender de conectividad. El registro se persiste en el dispositivo y se sincroniza despues. | F5: Dado un dispositivo sin conexion de datos, cuando el supervisor completa el registro de siembra de una cama, entonces el sistema lo persiste localmente, lo marca como 'pendiente de sincronizar' y muestra confirmacion visible sin requerir red. | G5: S2 - Director de Produccion | H5: Must | I5: =Criticidad!I5 -> 2.6 | J5: Confirmado
A6: RF-C02 | B6: Captura en campo | C6: El sistema debe permitir registrar el corte (produccion) de una cama por variedad, grado y fecha, sin conexion a internet. | D6: Supervisor de campo | E6: RN-02: el corte de una cama se registra por dia; una cama corta durante ~7 dias, no en un solo evento. | F6: Dado un dispositivo sin conexion, cuando el supervisor registra el corte de una cama para una fecha, entonces el sistema acepta multiples registros de corte para la misma cama en dias distintos del ciclo y los conserva por separado. | G6: S1 y S2 - Director de Produccion | H6: Must | I6: =Criticidad!I6 -> 2.65 | J6: Confirmado
A7: RF-C03 | B7: Sincronizacion | C7: El sistema debe sincronizar los registros capturados en el dispositivo con el repositorio central cuando haya conectividad, sin perder registros y sin duplicarlos. | D7: Sistema / Supervisor de campo | E7: RN-03: cada registro capturado se entrega al repositorio central exactamente una vez. Un registro no confirmado permanece pendiente en el dispositivo. | F7: Dado un dispositivo con N registros pendientes, cuando recupera conectividad, entonces el sistema sube los N registros, deja el contador de pendientes en cero y, si alguno falla, lo mantiene pendiente y lo lista de forma explicita al usuario. | G7: S2 - Director de Produccion / decision de arquitectura | H7: Must | I7: =Criticidad!I7 -> 3 | J7: Confirmado
A8: RF-C04 | B8: Sincronizacion | C8: El sistema debe detectar cuando dos registros distintos afectan la misma cama en la misma fecha y presentar el conflicto para resolucion humana, sin sobrescribir ninguno de forma automatica. | D8: Administrador de produccion y ventas | E8: RN-04: ante dos registros en conflicto, ninguno se descarta automaticamente. Prevalece la decision de un usuario con rol administrador. | F8: Dado dos registros de corte para la misma cama y fecha provenientes de dispositivos distintos, cuando ambos se sincronizan, entonces el sistema conserva los dos, marca la cama en estado 'conflicto' y no la incluye en el calculo de proyeccion hasta que un administrador resuelva. | G8: Inferido de S2 - pendiente de validar con el cliente | H8: Should | I8: =Criticidad!I8 -> 1.95 | J8: Inferido
A9: RF-C05 | B9: Validacion | C9: El sistema debe impedir el registro de un evento que sea imposible dentro del ciclo fenologico de la cama, y explicar al usuario por que lo rechaza, aun sin conexion. | D9: Supervisor de campo | E9: RN-05: entre siembra y primer corte deben transcurrir al menos los dias a corte minimos de la variedad, menos el margen de corrimiento admitido (hasta 15 dias de adelanto). | F9: Dado una cama sembrada hace 7 dias con una variedad cuyo ciclo minimo es 90 dias, cuando el supervisor intenta registrar un corte, entonces el sistema rechaza el registro sin conexion y muestra el motivo y el rango de fechas valido. | G9: S1 y S2 - Director de Produccion | H9: Must | I9: =Criticidad!I9 -> 2.75 | J9: Confirmado
A10: RF-C06 | B10: Validacion | C10: El sistema debe rechazar todo dato de produccion que implique una productividad superior al 100% de las plantas sembradas en la cama. | D10: Sistema | E10: RN-06: tallos registrados o proyectados por cama <= plantas sembradas en esa cama. Sin excepcion declarada. | F10: Dado una cama con 1.000 plantas sembradas, cuando se intenta registrar o calcular una produccion de 1.001 tallos o mas, entonces el sistema rechaza el valor e identifica el registro como dato erroneo. | G10: S2 - Director de Produccion | H10: Must | I10: =Criticidad!I10 -> 2.35 | J10: Confirmado
A11: RF-C07 | B11: Motor de proyeccion | C11: El sistema debe calcular los tallos proyectados de una cama a partir de su area, la densidad de siembra de la variedad y el porcentaje de productividad esperada de esa variedad. | D11: Administrador de produccion y ventas | E11: RN-07: plantas_sembradas = area_cama_m2 x densidad_siembra(variedad); tallos_proyectados = plantas_sembradas x %productividad_esperada(variedad), con %productividad entre 80% y 100%. | F11: Dado una cama de area conocida con variedad parametrizada, cuando se solicita la proyeccion, entonces el sistema devuelve tallos proyectados = area x densidad x %productividad, muestra los tres factores usados y nunca un valor mayor a las plantas sembradas. | G11: S2 - Director de Produccion | H11: Must | I11: =Criticidad!I11 -> 2.65 | J11: Confirmado
A12: RF-C08 | B12: Motor de proyeccion | C12: El sistema debe distribuir los tallos proyectados de una cama a lo largo de los dias que dura su corte, en vez de asignarlos todos a una sola fecha. | D12: Administrador de produccion y ventas | E12: RN-08: la produccion de una cama se reparte sobre la duracion de corte de su variedad segun una curva de distribucion parametrizable. | F12: Dado una cama con 900 tallos proyectados y una variedad con 7 dias de corte, cuando se consulta la proyeccion diaria, entonces el sistema entrega un valor por cada uno de los 7 dias cuya suma es 900. | G12: S2 - Director de Produccion | H12: Must | I12: =Criticidad!I12 -> 2.6 | J12: Confirmado
A13: RF-C09 | B13: Erradicaciones y bajas | C13: El sistema debe permitir registrar la erradicacion de una cama y descontar hacia adelante la produccion que quedaba proyectada para esa cama. | D13: Administrador de produccion y ventas | E13: RN-09: al erradicar una cama, el ciclo vuelve a cero y la produccion proyectada pendiente de esa cama se resta del total. La fecha de resiembra no es fija. | F13: Dado una cama con 900 tallos proyectados y ninguno cortado, cuando se registra su erradicacion, entonces la proyeccion agregada de la finca disminuye en 900 tallos a partir de la fecha de erradicacion y la cama queda en estado 'sin ciclo activo'. | G13: S2 - Director de Produccion | H13: Must | I13: =Criticidad!I13 -> 2.45 | J13: Confirmado
A14: RF-C10 | B14: Erradicaciones y bajas | C14: El sistema debe permitir registrar una baja de produccion, expresada en porcentaje o en tallos, y descontarla de la produccion estimada de la cama afectada. | D14: Supervisor de campo / Administrador de produccion y ventas | E14: RN-10: la baja se expresa en porcentaje o en tallos sobre la produccion estimada de una cama y una fecha. Se registra por formato en campo. | F14: Dado una cama con 900 tallos estimados, cuando se registra una baja del 10%, entonces la produccion estimada de esa cama pasa a 810 tallos y el sistema conserva el valor original, el porcentaje aplicado y el motivo. | G14: S1 y S2 - Director de Produccion | H14: Must | I14: =Criticidad!I14 -> 2.05 | J14: Confirmado
A15: RF-C11 | B15: Motor de proyeccion | C15: El sistema debe regenerar la proyeccion con la informacion acumulada al menos una vez por semana y conservar la version anterior de cada proyeccion generada. | D15: Administrador de produccion y ventas | E15: RN-11: la proyeccion se recalcula semanalmente como minimo, y bajo demanda cuando ocurre una erradicacion o una baja relevante. Cada version queda fechada e identificable. | F15: Dado un cierre de semana, cuando el sistema regenera la proyeccion, entonces publica una version nueva fechada y mantiene consultable la version inmediatamente anterior para comparacion. | G15: S2 - Director de Produccion | H15: Must | I15: =Criticidad!I15 -> 2.25 | J15: Confirmado
A16: RF-C12 | B16: Control de exactitud | C16: El sistema debe mostrar la desviacion entre el corte real y el corte proyectado, por cama, variedad y periodo, senalando los casos que salen de la banda de tolerancia parametrizada. | D16: Administrador de produccion y ventas | E16: RN-12: banda de aceptacion +/-10% sobre lo proyectado, parametrizable. El objetivo declarado es reducir la brecha, no solo mantenerse dentro de la banda. | F16: Dado una cama con 900 tallos proyectados y 850 cortados, cuando se consulta el control de exactitud, entonces el sistema muestra una desviacion de -5,6% y la clasifica dentro de la banda; con 780 tallos la clasifica fuera de banda. | G16: S2 - Director de Produccion | H16: Must | I16: =Criticidad!I16 -> 2.45 | J16: Confirmado
... A24: RF-C20 | B24: Captura asistida (propuesta del equipo) | C24: El sistema debe permitir al usuario describir un registro en lenguaje natural y debe presentarle la interpretacion resultante para su confirmacion explicita antes de persistir cualquier dato. | D24: Supervisor de campo | E24: RN-20: el asistente propone, el sistema valida, el usuario confirma. Nunca escritura silenciosa. Las validaciones RF-C05 y RF-C06 corren sobre el resultado interpretado. | F24: Dado un supervisor que dicta 'bloque 7 cama 12 corte 300 tallos', cuando el asistente interpreta la frase, entonces el sistema muestra los campos resueltos contra el catalogo de la finca, no persiste nada hasta la confirmacion del usuario y permite corregir cualquier campo antes de confirmar. | G24: Propuesta del equipo - no validada con el cliente | H24: Could | I24: =Criticidad!I24 -> 1.95 | J24: Propuesta equipo

Sheet Trazabilidad
A1: De lo que dijo el cliente al requisito
A2: La cita textual y la interpretacion nunca se mezclan. Si una fila no tiene cita, es propuesta del equipo y esta marcada como tal.
A4: ID | B4: Cita textual del cliente | C4: Hallazgo (que significa) | D4: Regla de negocio o restriccion | E4: Requisito derivado | F4: Origen
A5: RF-C01 | B5: "El formato de plagas y enfermedades se llena en una app totalmente local en el celular y sube a la nube despues." / "Que sea facil, que a veces las aplicaciones ponemos tanta arandela que es muy complicado." | C5: La finca ya opera una app movil offline para monitoreo fitosanitario. Existe precedente tecnico y cultural de captura movil sin red; la exigencia real no es la conexion sino la simplicidad. | D5: RN-01: la captura en campo no puede depender de conectividad. El registro se persiste en el dispositivo y se sincroniza despues. | E5: El sistema debe permitir registrar la siembra de una cama (bloque, nave, cama, variedad, fecha, cantidad de esquejes) sin conexion a internet, y confirmar al usuario que el registro quedo guardado. | F5: S2 - Director de Produccion
A6: RF-C02 | B6: "El supervisor llena formatos a lapiz y papel una hora al dia" y el practicante digita 4 horas por semana. | C6: Hoy la produccion se captura en papel y se redigita. Es el origen del 2% de error de captura y de los 8 dias de latencia. | D6: RN-02: el corte de una cama se registra por dia; una cama corta durante ~7 dias, no en un solo evento. | E6: El sistema debe permitir registrar el corte (produccion) de una cama por variedad, grado y fecha, sin conexion a internet. | F6: S1 y S2 - Director de Produccion
A7: RF-C03 | B7: "Sube a la nube despues." / "La informacion tarda 8 dias en llegar a planeacion y gerencia." | C7: La sincronizacion diferida es la pieza que convierte la captura offline en dato utilizable. Es tambien el punto donde el sistema puede perder informacion sin que nadie se entere. | D7: RN-03: cada registro capturado se entrega al repositorio central exactamente una vez. Un registro no confirmado permanece pendiente en el dispositivo. | E7: El sistema debe sincronizar los registros capturados en el dispositivo con el repositorio central cuando haya conectividad, sin perder registros y sin duplicarlos. | F7: S2 - Director de Produccion / decision de arquitectura
A8: RF-C04 | B8: "Solo 3 personas ingresan informacion: 1 supervisor y 2 auxiliares." | C8: Tres capturadores sobre 1.525 camas hacen improbable pero no imposible el solapamiento. En un esquema offline los dos registros son validos localmente y solo chocan al sincronizar. | D8: RN-04: ante dos registros en conflicto, ninguno se descarta automaticamente. Prevalece la decision de un usuario con rol administrador. | E8: El sistema debe detectar cuando dos registros distintos afectan la misma cama en la misma fecha y presentar el conflicto para resolucion humana, sin sobrescribir ninguno de forma automatica. | F8: Inferido de S2 - pendiente de validar con el cliente
A9: RF-C05 | B9: "No se puede registrar corte en una cama sembrada hace una semana." | C9: El cliente pidio validaciones duras de forma explicita. Como la captura es offline, la validacion debe ejecutarse en el dispositivo: validar solo en el servidor llegaria 8 dias tarde. | D9: RN-05: entre siembra y primer corte deben transcurrir al menos los dias a corte minimos de la variedad, menos el margen de corrimiento admitido (hasta 15 dias de adelanto). | E9: El sistema debe impedir el registro de un evento que sea imposible dentro del ciclo fenologico de la cama, y explicar al usuario por que lo rechaza, aun sin conexion. | F9: S1 y S2 - Director de Produccion
A10: RF-C06 | B10: "Nunca puede superar el 100%: si el sistema arroja mas tallos que plantas sembradas, hay un dato malo." | C10: El cliente entrego una regla de consistencia absoluta y verificable. Es la unica cota dura que dio para el motor de proyeccion. | D10: RN-06: tallos registrados o proyectados por cama <= plantas sembradas en esa cama. Sin excepcion declarada. | E10: El sistema debe rechazar todo dato de produccion que implique una productividad superior al 100% de las plantas sembradas en la cama. | F10: S2 - Director de Produccion
A11: RF-C07 | B11: "1.000 plantas sembradas, 90% de productividad, da 900 tallos proyectados." | C11: Es la formula nuclear del producto y la unica que el cliente verbalizo completa. Todo lo demas del sistema existe para alimentarla o para consumirla. | D11: RN-07: plantas_sembradas = area_cama_m2 x densidad_siembra(variedad); tallos_proyectados = plantas_sembradas x %productividad_esperada(variedad), con %productividad entre 80% y 100%. | E11: El sistema debe calcular los tallos proyectados de una cama a partir de su area, la densidad de siembra de la variedad y el porcentaje de productividad esperada de esa variedad. | F11: S2 - Director de Produccion
A12: RF-C08 | B12: "Una cama no corta todo en un dia. El corte dura alrededor de 7 dias, segun variedad." | C12: Sin curva de distribucion, la proyeccion diaria que necesita el gerente de produccion es inutilizable, aunque el total semanal sea correcto. | D12: RN-08: la produccion de una cama se reparte sobre la duracion de corte de su variedad segun una curva de distribucion parametrizable. | E12: El sistema debe distribuir los tallos proyectados de una cama a lo largo de los dias que dura su corte, en vez de asignarlos todos a una sola fecha. | F12: S2 - Director de Produccion
A13: RF-C09 | B13: "Se debe digitar para que el sistema reste esa produccion proyectada." / "Lo que ya estaba vendido de ahi se cancela o se compra a terceros." | C13: Es la instruccion mas concreta que dio el cliente sobre comportamiento del sistema. Conecta directo con el 8% de las ventas que hoy se cubre comprando a terceros o cancelando ordenes. | D13: RN-09: al erradicar una cama, el ciclo vuelve a cero y la produccion proyectada pendiente de esa cama se resta del total. La fecha de resiembra no es fija. | E13: El sistema debe permitir registrar la erradicacion de una cama y descontar hacia adelante la produccion que quedaba proyectada para esa cama. | F13: S2 - Director de Produccion
A14: RF-C10 | B14: "Baja de produccion: cuando algo falla y parte del producto ya no sirve para venta, se descuenta un porcentaje de la produccion estimada. La idea es que sea de un dia para otro, hoy pasa cada semana." | C14: El cliente nombro explicitamente la latencia actual (una semana) y la deseada (un dia). Esa brecha es requisito, no aspiracion. | D14: RN-10: la baja se expresa en porcentaje o en tallos sobre la produccion estimada de una cama y una fecha. Se registra por formato en campo. | E14: El sistema debe permitir registrar una baja de produccion, expresada en porcentaje o en tallos, y descontarla de la produccion estimada de la cama afectada. | F14: S1 y S2 - Director de Produccion
A15: RF-C11 | B15: "Hoy se ajusta mensualmente o cuando es necesario. Se quiere que sea semanal." | C15: El ajuste semanal es una brecha declarada entre el estado actual y el deseado. Conservar versiones no lo pidio el cliente, pero sin ello es imposible medir si la proyeccion mejoro. | D15: RN-11: la proyeccion se recalcula semanalmente como minimo, y bajo demanda cuando ocurre una erradicacion o una baja relevante. Cada version queda fechada e identificable. | E15: El sistema debe regenerar la proyeccion con la informacion acumulada al menos una vez por semana y conservar la version anterior de cada proyeccion generada. | F15: S2 - Director de Produccion
... A24: RF-C20 | B24: "Que sea facil, que a veces las aplicaciones ponemos tanta arandela que es muy complicado." El requisito de facilidad es del cliente; la captura por lenguaje natural NO lo es. | C24: Este RF no salio de la entrevista: es una propuesta de diseno del equipo para atender la exigencia de rapidez y baja digitalizacion. Debe documentarse como tal y sostenerse con una medicion, no con intuicion. | D24: RN-20: el asistente propone, el sistema valida, el usuario confirma. Nunca escritura silenciosa. Las validaciones RF-C05 y RF-C06 corren sobre el resultado interpretado. | E24: El sistema debe permitir al usuario describir un registro en lenguaje natural y debe presentarle la interpretacion resultante para su confirmacion explicita antes de persistir cualquier dato. | F24: Propuesta del equipo - no validada con el cliente

Sheet Criticidad
A1: Matriz de criticidad
A2: Puntaje 0 a 3 en cada eje. Los pesos de la fila 3 son editables y el indice se recalcula solo. Suma de pesos en L3.
A3: Pesos -> | E3: 0.4 | F3: 0.2 | G3: 0.25 | H3: 0.15 | I3: =SUM(E3:H3) -> 1 | J3: <- debe dar 100%
A4: ID | B4: Modulo | C4: Requisito (resumen) | D4: Prio. | E4: Sin esto no hay producto | F4: Riesgo arquitectonico | G4: Alto impacto de negocio | H4: Alto riesgo de fallo | I4: Indice ponderado | J4: Nivel
A5: RF-C01 | B5: Captura en campo | C5: El sistema debe permitir registrar la siembra de una cama (bloque, nave, cama, variedad, fecha, cantidad de esquejes) sin conexion a internet, y confi... | D5: Must | E5: 3 | F5: 3 | G5: 2 | H5: 2 | I5: =SUMPRODUCT(E5:H5,$E$3:$H$3) -> 2.6 | J5: =IF(I5>=2.5,"Critico alto",IF(I5>=1.8,"Critico","Relevante")) -> Critico alto
A6: RF-C02 | B6: Captura en campo | C6: El sistema debe permitir registrar el corte (produccion) de una cama por variedad, grado y fecha, sin conexion a internet. | D6: Must | E6: 3 | F6: 2 | G6: 3 | H6: 2 | I6: =SUMPRODUCT(E6:H6,$E$3:$H$3) -> 2.65 | J6: =IF(I6>=2.5,"Critico alto",IF(I6>=1.8,"Critico","Relevante")) -> Critico alto
A7: RF-C03 | B7: Sincronizacion | C7: El sistema debe sincronizar los registros capturados en el dispositivo con el repositorio central cuando haya conectividad, sin perder registros y sin... | D7: Must | E7: 3 | F7: 3 | G7: 3 | H7: 3 | I7: =SUMPRODUCT(E7:H7,$E$3:$H$3) -> 3 | J7: =IF(I7>=2.5,"Critico alto",IF(I7>=1.8,"Critico","Relevante")) -> Critico alto
A8: RF-C04 | B8: Sincronizacion | C8: El sistema debe detectar cuando dos registros distintos afectan la misma cama en la misma fecha y presentar el conflicto para resolucion humana, sin s... | D8: Should | E8: 1 | F8: 3 | G8: 2 | H8: 3 | I8: =SUMPRODUCT(E8:H8,$E$3:$H$3) -> 1.95 | J8: =IF(I8>=2.5,"Critico alto",IF(I8>=1.8,"Critico","Relevante")) -> Critico
A9: RF-C05 | B9: Validacion | C9: El sistema debe impedir el registro de un evento que sea imposible dentro del ciclo fenologico de la cama, y explicar al usuario por que lo rechaza, a... | D9: Must | E9: 3 | F9: 3 | G9: 2 | H9: 3 | I9: =SUMPRODUCT(E9:H9,$E$3:$H$3) -> 2.75 | J9: =IF(I9>=2.5,"Critico alto",IF(I9>=1.8,"Critico","Relevante")) -> Critico alto
A10: RF-C06 | B10: Validacion | C10: El sistema debe rechazar todo dato de produccion que implique una productividad superior al 100% de las plantas sembradas en la cama. | D10: Must | E10: 3 | F10: 1 | G10: 2 | H10: 3 | I10: =SUMPRODUCT(E10:H10,$E$3:$H$3) -> 2.35 | J10: =IF(I10>=2.5,"Critico alto",IF(I10>=1.8,"Critico","Relevante")) -> Critico
A11: RF-C07 | B11: Motor de proyeccion | C11: El sistema debe calcular los tallos proyectados de una cama a partir de su area, la densidad de siembra de la variedad y el porcentaje de productivida... | D11: Must | E11: 3 | F11: 2 | G11: 3 | H11: 2 | I11: =SUMPRODUCT(E11:H11,$E$3:$H$3) -> 2.65 | J11: =IF(I11>=2.5,"Critico alto",IF(I11>=1.8,"Critico","Relevante")) -> Critico alto
A12: RF-C08 | B12: Motor de proyeccion | C12: El sistema debe distribuir los tallos proyectados de una cama a lo largo de los dias que dura su corte, en vez de asignarlos todos a una sola fecha. | D12: Must | E12: 3 | F12: 1 | G12: 3 | H12: 3 | I12: =SUMPRODUCT(E12:H12,$E$3:$H$3) -> 2.6 | J12: =IF(I12>=2.5,"Critico alto",IF(I12>=1.8,"Critico","Relevante")) -> Critico alto
A13: RF-C09 | B13: Erradicaciones y bajas | C13: El sistema debe permitir registrar la erradicacion de una cama y descontar hacia adelante la produccion que quedaba proyectada para esa cama. | D13: Must | E13: 3 | F13: 1 | G13: 3 | H13: 2 | I13: =SUMPRODUCT(E13:H13,$E$3:$H$3) -> 2.45 | J13: =IF(I13>=2.5,"Critico alto",IF(I13>=1.8,"Critico","Relevante")) -> Critico
A14: RF-C10 | B14: Erradicaciones y bajas | C14: El sistema debe permitir registrar una baja de produccion, expresada en porcentaje o en tallos, y descontarla de la produccion estimada de la cama afe... | D14: Must | E14: 2 | F14: 1 | G14: 3 | H14: 2 | I14: =SUMPRODUCT(E14:H14,$E$3:$H$3) -> 2.05 | J14: =IF(I14>=2.5,"Critico alto",IF(I14>=1.8,"Critico","Relevante")) -> Critico
A15: RF-C11 | B15: Motor de proyeccion | C15: El sistema debe regenerar la proyeccion con la informacion acumulada al menos una vez por semana y conservar la version anterior de cada proyeccion ge... | D15: Must | E15: 2 | F15: 2 | G15: 3 | H15: 2 | I15: =SUMPRODUCT(E15:H15,$E$3:$H$3) -> 2.25 | J15: =IF(I15>=2.5,"Critico alto",IF(I15>=1.8,"Critico","Relevante")) -> Critico
A16: RF-C12 | B16: Control de exactitud | C16: El sistema debe mostrar la desviacion entre el corte real y el corte proyectado, por cama, variedad y periodo, senalando los casos que salen de la ban... | D16: Must | E16: 3 | F16: 1 | G16: 3 | H16: 2 | I16: =SUMPRODUCT(E16:H16,$E$3:$H$3) -> 2.45 | J16: =IF(I16>=2.5,"Critico alto",IF(I16>=1.8,"Critico","Relevante")) -> Critico
... A24: RF-C20 | B24: Captura asistida (propuesta del equipo) | C24: El sistema debe permitir al usuario describir un registro en lenguaje natural y debe presentarle la interpretacion resultante para su confirmacion exp... | D24: Could | E24: 1 | F24: 3 | G24: 2 | H24: 3 | I24: =SUMPRODUCT(E24:H24,$E$3:$H$3) -> 1.95 | J24: =IF(I24>=2.5,"Critico alto",IF(I24>=1.8,"Critico","Relevante")) -> Critico
B26: Resumen
B27: RF criticos totales | C27: =COUNTA(A5:A24) -> 20
B28: Nivel 'Critico alto' | C28: =COUNTIF(J5:J24,"Critico alto") -> 6
B29: Nivel 'Critico' | C29: =COUNTIF(J5:J24,"Critico") -> 13
B30: Must | C30: =COUNTIF(D5:D24,"Must") -> 17
B31: Indice promedio | C31: =ROUND(AVERAGE(I5:I24),2) -> 2.27
B32: Indice maximo | C32: =ROUND(MAX(I5:I24),2) -> 3
B34: Escala de cada eje
B35: 0 | C35: No aplica
B36: 1 | C36: Bajo
B37: 2 | C37: Medio
B38: 3 | C38: Alto

Sheet Mapa de calidad
A1: RF critico -> atributos de calidad candidatos
A2: Insumo para escribir los escenarios. Aun NO son escenarios: falta la medida de respuesta, que es justo lo que hay que negociar con el cliente.
A4: ID | B4: Requisito (resumen) | C4: Indice | D4: Atributos de calidad que tensiona | E4: Por que tensiona ese atributo | F4: Que falta para escribir el escenario
A5: RF-C01 | B5: El sistema debe permitir registrar la siembra de una cama (bloque, nave, cama, variedad, fecha, cantidad de esquejes) sin conexion a interne... | C5: =Criticidad!I5 -> 2.6 | D5: Disponibilidad; Confiabilidad; Experiencia de usuario | E5: La captura tiene que funcionar cuando el respaldo tecnico no esta disponible, y la tiene que usar gente de baja digitalizacion mas rapido que el papel. | F5: Falta el tiempo maximo aceptable de confirmacion (el boceto de S2 uso 3 s). Falta la lista definitiva de campos obligatorios del formato de siembra.
A6: RF-C02 | B6: El sistema debe permitir registrar el corte (produccion) de una cama por variedad, grado y fecha, sin conexion a internet. | C6: =Criticidad!I6 -> 2.65 | D6: Disponibilidad; Confiabilidad; Experiencia de usuario | E6: Mismo caso que la siembra, pero con volumen: en temporada pico los registros suben 60%. | F6: Falta el catalogo de grados y calidades de esta finca (BR-11). Sin el no se sabe con que granularidad se registra el corte.
A7: RF-C03 | B7: El sistema debe sincronizar los registros capturados en el dispositivo con el repositorio central cuando haya conectividad, sin perder regis... | C7: =Criticidad!I7 -> 3 | D7: Confiabilidad; Disponibilidad; Interoperatividad | E7: Es el punto unico donde el sistema puede perder un dato de forma silenciosa. Confiabilidad es el atributo numero 1 del cliente. | F7: Falta definir la ventana maxima aceptable entre captura y disponibilidad del dato (hoy 8 dias; el objetivo declarado es 'de un dia para otro').
A8: RF-C04 | B8: El sistema debe detectar cuando dos registros distintos afectan la misma cama en la misma fecha y presentar el conflicto para resolucion hum... | C8: =Criticidad!I8 -> 1.95 | D8: Confiabilidad; Trazabilidad | E8: Un conflicto mal resuelto contamina la proyeccion sin que nadie lo note. | F8: No se pregunto al cliente si dos personas pueden registrar la misma cama. Hay que confirmarlo: si nunca ocurre, este RF baja de prioridad.
A9: RF-C05 | B9: El sistema debe impedir el registro de un evento que sea imposible dentro del ciclo fenologico de la cama, y explicar al usuario por que lo ... | C9: =Criticidad!I9 -> 2.75 | D9: Confiabilidad; Experiencia de usuario; Capacidad para ser administrado | E9: La validacion tiene que correr en el dispositivo, no en el servidor, o llega 8 dias tarde. | F9: Falta la tabla completa de dias a corte por variedad. Falta decidir si el rechazo es duro o admite anulacion por parte de un administrador.
A10: RF-C06 | B10: El sistema debe rechazar todo dato de produccion que implique una productividad superior al 100% de las plantas sembradas en la cama. | C10: =Criticidad!I10 -> 2.35 | D10: Confiabilidad; Trazabilidad | E10: Es la unica cota dura verificable que dio el cliente. Si falla, el motor entrega numeros imposibles. | F10: Confirmar si la cota aplica al acumulado de los ~7 dias de corte o a cada registro diario. Hoy se asume que al acumulado.
A11: RF-C07 | B11: El sistema debe calcular los tallos proyectados de una cama a partir de su area, la densidad de siembra de la variedad y el porcentaje de pr... | C11: =Criticidad!I11 -> 2.65 | D11: Confiabilidad; Rendimiento; Trazabilidad | E11: Es la formula nuclear. Debe responder rapido sobre 1.525 camas y ser reproducible: dos ejecuciones con los mismos datos dan el mismo numero. | F11: BR-23 abierta: no se sabe de donde sale el %productividad esperada por variedad (historico, tabla del agronomo o ficha del proveedor). Sin esa fuente el motor no puede correr.
A12: RF-C08 | B12: El sistema debe distribuir los tallos proyectados de una cama a lo largo de los dias que dura su corte, en vez de asignarlos todos a una sol... | C12: =Criticidad!I12 -> 2.6 | D12: Confiabilidad; Rendimiento | E12: Sin curva no hay proyeccion diaria, que es lo que consume el gerente de produccion. | F12: BR-23 abierta: la curva no existe hoy. Es el ultimo hueco del motor. Sin ella solo se puede proyectar a nivel semanal.
A13: RF-C09 | B13: El sistema debe permitir registrar la erradicacion de una cama y descontar hacia adelante la produccion que quedaba proyectada para esa cama... | C13: =Criticidad!I13 -> 2.45 | D13: Confiabilidad; Trazabilidad; Disponibilidad | E13: El recalculo debe estar disponible el mismo dia: de ahi depende cancelar una orden o comprar a terceros. | F13: Definir que pasa con la produccion ya cortada de esa cama antes de la erradicacion, y si la erradicacion parcial de una cama es posible.
A14: RF-C10 | B14: El sistema debe permitir registrar una baja de produccion, expresada en porcentaje o en tallos, y descontarla de la produccion estimada de l... | C14: =Criticidad!I14 -> 2.05 | D14: Confiabilidad; Trazabilidad | E14: El cliente pidio pasar de una semana a un dia de latencia. Es un requisito de oportunidad del dato. | F14: No hay criterio objetivo para el porcentaje de baja: hoy es juicio del director. Falta el catalogo de motivos de baja.
A15: RF-C11 | B15: El sistema debe regenerar la proyeccion con la informacion acumulada al menos una vez por semana y conservar la version anterior de cada pro... | C15: =Criticidad!I15 -> 2.25 | D15: Confiabilidad; Rendimiento; Trazabilidad; Capacidad | E15: Regenerar semanalmente sobre 1.525 camas y 1,5 anos de horizonte es el mayor consumo de computo del sistema. | F15: Definir si el recalculo es programado o disparado por el usuario, y cuanto puede tardar sobre 1.525 camas y un horizonte de 1,5 anos.
A16: RF-C12 | B16: El sistema debe mostrar la desviacion entre el corte real y el corte proyectado, por cama, variedad y periodo, senalando los casos que salen... | C16: =Criticidad!I16 -> 2.45 | D16: Confiabilidad; Trazabilidad; Experiencia de usuario | E16: Es la metrica de exito. Si el numero que muestra no es confiable, el proyecto no se puede evaluar. | F16: BR-21 abierta y critica: no se sabe a que nivel de agregacion se miden el -6% y el +/-10%. De eso depende la linea base del proyecto.
... A24: RF-C20 | B24: El sistema debe permitir al usuario describir un registro en lenguaje natural y debe presentarle la interpretacion resultante para su confir... | C24: =Criticidad!I24 -> 1.95 | D24: Accesibilidad; Experiencia de usuario; Confiabilidad; Rendimiento; Portabilidad | E24: Corre en gama baja, sin red, con ruido de invernadero y vocabulario tecnico que los transcriptores automaticos ya destrozaron. Toca casi todos los atributos a la vez. | F24: BR-24 abierta: el cliente puso accesibilidad en el puesto 10 de 14, probablemente por no entender el termino. Sin reabrir esa fila, este RF no tiene respaldo. Ademas falta la medicion contra un formulario optimizado.
B27: Cuantos RF criticos tocan cada atributo
B28: Atributo | C28: Prio. cliente | D28: RF que lo tocan | E28: Lectura
B29: Confiabilidad | C29: 1 | D29: =COUNTIF($D$5:$D$25,"*"&B29&";*")+COUNTIF($D$5:$D$25,"*"&B29) -> 19 | E29: Coincide: es el atributo que mas RF criticos tocan y el que el cliente puso primero.
B30: Experiencia de usuario | C30: 2 | D30: =COUNTIF($D$5:$D$25,"*"&B30&";*")+COUNTIF($D$5:$D$25,"*"&B30) -> 7 | E30: Coincide con la insistencia del cliente en que sea facil.
B31: Disponibilidad | C31: 3 | D31: =COUNTIF($D$5:$D$25,"*"&B31&";*")+COUNTIF($D$5:$D$25,"*"&B31) -> 5 | E31: Tolerancia declarada: ~1 hora de caida. Cuatro horas es demasiado.
B32: Interoperatividad | C32: 3 | D32: =COUNTIF($D$5:$D$25,"*"&B32&";*")+COUNTIF($D$5:$D$25,"*"&B32) -> 1 | E32: Aparece poco en los RF criticos porque el sistema actual sigue sin identificarse.
B33: Seguridad | C33: 4 | D33: =COUNTIF($D$5:$D$25,"*"&B33&";*")+COUNTIF($D$5:$D$25,"*"&B33) -> 3 | E33: Concentrada en una sola regla: precio de venta. Poco extendida pero no negociable.
B34: Rendimiento | C34: 5 | D34: =COUNTIF($D$5:$D$25,"*"&B34&";*")+COUNTIF($D$5:$D$25,"*"&B34) -> 6 | E34: Ligado al recalculo semanal y a la inferencia en dispositivo de gama baja.
B35: Capacidad para ser soportado | C35: 6 | D35: =COUNTIF($D$5:$D$25,"*"&B35&";*")+COUNTIF($D$5:$D$25,"*"&B35) -> 2 | E35: -
B36: Capacidad para ser administrado | C36: 7 | D36: =COUNTIF($D$5:$D$25,"*"&B36&";*")+COUNTIF($D$5:$D$25,"*"&B36) -> 2 | E36: La parametrizacion es lo que evita depender del equipo de desarrollo. El cliente lo puso en 7; el diseno sugiere mas arriba.
B37: Trazabilidad | C37: 8 | D37: =COUNTIF($D$5:$D$25,"*"&B37&";*")+COUNTIF($D$5:$D$25,"*"&B37) -> 9 | E37: El cliente la puso en 8, pero es requisito de alcance explicito (hasta la cama de origen). Revisar.
B38: Capacidad | C38: 9 | D38: =COUNTIF($D$5:$D$25,"*"&B38&";*")+COUNTIF($D$5:$D$25,"*"&B38) -> 2 | E38: Pico de temporada +60% en registros. Falta el volumen absoluto.
B39: Accesibilidad | C39: 10 | D39: =COUNTIF($D$5:$D$25,"*"&B39&";*")+COUNTIF($D$5:$D$25,"*"&B39) -> 1 | E39: TENSION ABIERTA (BR-24): definida como capacidad de ser usado por personas con baja digitalizacion. Es la premisa del RF-C20 y el cliente la puso casi al final. Reabrir con la definicion explicita.
B40: Portabilidad | C40: 11 | D40: =COUNTIF($D$5:$D$25,"*"&B40&";*")+COUNTIF($D$5:$D$25,"*"&B40) -> 1 | E40: -
... B42: Seguridad de funcionamiento (safety) | C42: 14 | D42: =COUNTIF($D$5:$D$25,"*"&B42&";*")+COUNTIF($D$5:$D$25,"*"&B42) -> 0 | E42: Sin evidencia de que aplique en este alcance.

Sheet Escenarios - esqueleto
A1: Esqueleto de escenarios de calidad
A2: Estructura vacia lista para llenar en la siguiente iteracion. La columna 'Medida de respuesta' es la que hay que negociar con el cliente: hoy casi todas estan sin numero.
A4: ID esc. | B4: RF asociado | C4: Atributo | D4: Fuente del estimulo | E4: Estimulo | F4: Artefacto | G4: Entorno | H4: Respuesta esperada | I4: Medida de respuesta | J4: Estado
A5: ESC-01 | B5: RF-C01 | C5: Disponibilidad | D5: Supervisor de campo | E5: Registra la siembra de una cama | F5: App movil de captura | G5: En campo, sin cobertura de red | H5: El registro queda persistido en el dispositivo y confirmado en pantalla | I5: PENDIENTE - el boceto de S2 uso 3 s. Confirmar con el cliente | J5: Por definir
A6: ESC-02 | B6: RF-C03 | C6: Confiabilidad | D6: Dispositivo movil | E6: Recupera conectividad con N registros pendientes | F6: Servicio de sincronizacion | G6: Fin de jornada, red intermitente | H6: Los N registros llegan al repositorio central exactamente una vez | I6: PENDIENTE - 0 registros perdidos; % de duplicados aceptable = 0 | J6: Por definir
A7: ESC-03 | B7: RF-C05 | C7: Confiabilidad | D7: Supervisor de campo | E7: Intenta registrar un corte imposible segun el ciclo | F7: Motor de validacion en dispositivo | G7: Sin conexion | H7: El sistema rechaza el registro y explica el motivo | I7: PENDIENTE - 100% de los casos imposibles rechazados, sin red | J7: Por definir
A8: ESC-04 | B8: RF-C11 | C8: Rendimiento | D8: Programador de tareas | E8: Dispara el recalculo semanal de la proyeccion | F8: Motor de proyeccion | G8: 1.525 camas, horizonte 1,5 anos, temporada pico | H8: La proyeccion nueva queda publicada | I8: PENDIENTE - tiempo maximo de recalculo. Sin dato del cliente | J8: Por definir
A9: ESC-05 | B9: RF-C09 | C9: Disponibilidad | D9: Administrador de produccion | E9: Registra la erradicacion de una cama | F9: Motor de proyeccion | G9: Dia habil, sistema en operacion | H9: La proyeccion agregada se ajusta descontando esa cama | I9: PENDIENTE - el cliente hablo de 'de un dia para otro'. Confirmar si aplica aqui | J9: Por definir
A10: ESC-06 | B10: RF-C15 | C10: Seguridad | D10: Supervisor de campo | E10: Consulta o exporta un reporte con informacion comercial | F10: Capa de autorizacion | G10: Cualquier canal: pantalla, reporte, exportacion | H10: El precio de venta no aparece ni es recuperable | I10: 0 apariciones del precio de venta en cualquier canal | J10: Propuesto
A11: ESC-07 | B11: RF-C20 | C11: Accesibilidad | D11: Supervisor de baja digitalizacion | E11: Dicta un registro en lenguaje natural en un invernadero con ruido | F11: Asistente de captura local | G11: Dispositivo de gama baja, sin red, ruido ambiente | H11: El sistema propone la interpretacion correcta contra el catalogo de la finca | I11: PENDIENTE - % de acierto minimo y tiempo maximo. Requiere medicion, no estimacion | J11: Por definir
A12: ESC-08 | B12: RF-C12 | C12: Confiabilidad | D12: Administrador de produccion | E12: Consulta la desviacion entre corte real y proyectado | F12: Modulo de control de exactitud | G12: Cierre de semana | H12: El sistema muestra la desviacion y la clasifica dentro o fuera de banda | I12: BLOQUEADO por BR-21 - falta el nivel de agregacion al que se mide | J12: Bloqueado

Sheet Brechas que bloquean
A1: Brechas abiertas que condicionan estos requisitos
A2: Cada fila es algo que, sin resolver, deja un RF critico sin poder cerrarse o sin poder convertirse en escenario medible.
A4: ID | B4: Brecha | C4: RF afectados | D4: Por que bloquea | E4: A quien se le pregunta | F4: Estado
A5: BR-21 | B5: A que nivel de agregacion se miden el -6% actual y el +/-10% objetivo | C5: RF-C12 | D5: Define la linea base y la metrica de exito del proyecto. Si el 6% es finca/ano y el 10% es cama/semana, la meta no es mas floja de lo que ya logran; si es al mismo nivel, si lo es. | E5: Director de Produccion | F5: Abierta
A6: BR-23 | B6: De donde sale el %productividad esperada por variedad y como se reparten los tallos en los ~7 dias de corte | C6: RF-C07, RF-C08 | D6: Es el ultimo hueco del motor. Sin la fuente del porcentaje no hay proyeccion; sin la curva no hay proyeccion diaria. | E6: Director de Produccion / Ing. agronomo | F6: Abierta
A7: BR-22 | B7: 9 variedades activas o ~300 con subvariedades | C7: RF-C13, RF-C20 | D7: Cambia el dimensionamiento del modelo de datos, de la interfaz de parametrizacion y del catalogo cerrado del asistente de captura. | E7: Director de Produccion | F7: Abierta
A8: BR-24 | B8: Accesibilidad quedo en el puesto 10 de 14 pese a ser la premisa del asistente de captura | C8: RF-C20 | D8: El propio cliente repitio que sea facil y puso experiencia de usuario en 2. Probablemente no entendio el termino. Sin reabrir la fila, el RF-C20 no tiene respaldo del cliente. | E8: Director de Produccion | F8: Abierta
A9: BR-11 | B9: Catalogo de grados y calidades de la finca | C9: RF-C02, RF-C14 | D9: Sin el no se sabe con que granularidad se registra el corte ni como se agrupa la produccion proyectada para ventas. | E9: Director de Produccion | F9: Abierta
A10: BR-N1 | B10: Tiempo maximo aceptable de confirmacion de captura en campo | C10: RF-C01, RF-C02, RF-C20 | D10: Es el numero que convierte 'que sea facil' en algo verificable. Sin el, ESC-01 y ESC-07 no tienen medida de respuesta. | E10: Director de Produccion / medicion en campo | F10: Abierta
A11: BR-N2 | B11: El sistema actual sigue sin identificarse (nombre, alcance, datos) | C11: RF-C03, RF-C13 | D11: No se sabe si FlorLogic reemplaza, alimenta o convive con lo existente. Condiciona toda la interoperatividad. | E11: Director de Produccion / Ing. de sistemas | F11: Abierta
A12: BR-N3 | B12: Los documentos prometidos no han llegado (plan de siembra, presupuestos, formatos llenos, historico) | C12: Todos | D12: Un formato en papel lleno contesta veinte preguntas que nunca se hicieron. Es el bloqueo real del levantamiento. | E12: Director de Produccion | F12: Abierta
A13: BR-N4 | B13: Puede una misma cama ser registrada por dos capturadores en la misma fecha | C13: RF-C04 | D13: Si nunca ocurre, RF-C04 baja de Should a Could y se simplifica la arquitectura de sincronizacion. | E13: Director de Produccion | F13: No preguntada
A14: BR-N5 | B14: Duracion de la ventana de sesion offline y que pasa si se pierde un dispositivo con registros sin sincronizar | C14: RF-C16 | D14: Es donde seguridad y disponibilidad chocan. La decision no puede quedar implicita. | E14: Equipo / Director de Produccion | F14: No preguntada
